Workbook

Sheet CPI Log
A1: 1 · YOUR COLUMNS | C1: same order as your old tab → paste your old rows at A4 with Ctrl+Shift+V (values only) | L1: 2 · CPI NUMBER | N1: 3 · CANDLE CLOSE | Q1: 4 · AFTER THE 1st MINUTE | X1: 5 · ICT CONTEXT | AE1: 6 · TRADE & REVIEW
A2: CPI Release Date | B2: Day | C2: Wick | D2: Wick pts | E2: Main Move | F2: 15sec move | G2: 30sec move | H2: 1min move | I2: Straddle | J2: Scam Wick (15 sec before) | K2: Notes | L2: CPI vs forecast | M2: Move vs data (auto) | N2: 1m candle close | O2: 5m candle close | P2: 15m candle close | Q2: 1-min HIGH taken (BSL) – when? | R2: 1-min LOW taken (SSL) – when? | S2: Deepest pullback % | T2: Back to 8:30 open – when? | U2: At the open, price… | V2: Outcome 8:31–8:45 (auto) | W2: First side taken (auto) | X2: Daily bias (before 8:30) | Y2: 8:30 open vs Midnight open | Z2: Liquidity taken by wick | AA2: Liquidity taken by main move (by 8:45) | AB2: HTF PD array at extreme (optional) | AC2: 1m FVG from main move | AD2: SMT with ES (optional) | AE2: Setup | AF2: Result (R) | AG2: Chart link
A3: date | B3: auto | C3: ▼ Up / Down / No Wick | D3: pts | E3: ▼ Up / Down | F3: pts | G3: pts | H3: pts | I3: ▼ TP / SL / BE / N/A | J3: pts | K3: text | L3: ▼ Hotter / Cooler / In line / Mixed | M3: auto | N3: ▼ Top / Middle / Bottom | O3: ▼ Top / Middle / Bottom | P3: ▼ Top / Middle / Bottom | Q3: ▼ time window | R3: ▼ time window | S3: 0-200 (no % sign) | T3: ▼ time window | U3: ▼ pick | V3: auto | W3: auto | X3: ▼ pick | Y3: ▼ Above / Below | Z3: ▼ biggest level | AA3: ▼ biggest level | AB3: ▼ pick | AC3: ▼ pick | AD3: ▼ Yes / No | AE3: ▼ pick | AF3: e.g. 2 or -1 | AG3: TradingView link
B4: =IF(ISNUMBER(A4),TEXT(A4,"ddd"),"") | M4: =IF(OR(L4="",AND(E4<>"Up",E4<>"Down")),"",IF(OR(L4="In line",L4="Mixed"),"Neutral data",IF(OR(AND(L4="Hotter",E4="Down"),AND(L4="Cooler",E4="Up")),"With data","Against data"))) | V4: =IF(OR(AND(E4<>"Up",E4<>"Down"),NOT(ISNUMBER(S4)),IF(E4="Up",Q4,R4)=""),"",IF(S4>=100,"Back to open",IF(OR(IF(E4="Up",Q4,R4)="1-5 min",IF(E4="Up",Q4,R4)="5-15 min"),"Continued",IF(S4>=50,"Partial retrace","Stalled / chop")))) | W4: =IF(OR(Q4="",R4=""),"",IFERROR(IF(AND(Q4="Not by 16:00",R4="Not by 16:00"),"Neither taken",IF(FIND("|"&Q4&"|","|1-5 min|5-15 min|15-60 min|9:30-11:00|11:00-16:00|Not by 16:00|")=FIND("|"&R4&"|","|1-5 min|5-15 min|15-60 min|9:30-11:00|11:00-16:00|Not by 16:00|"),"Same window",IF(FIND("|"&Q4&"|","|1-5 min|5-15 min|15-60 min|9:30-11:00|11:00-16:00|Not by 16:00|")<FIND("|"&R4&"|","|1-5 min|5-15 min|15-60 min|9:30-11:00|11:00-16:00|Not by 16:00|"),IF(E4="Up","High first (main side)",IF(E4="Down","High first (wick side)","High first")),IF(E4="Down","Low first (main side)",IF(E4="Up","Low first (wick side)","Low first"))))),"Check entries"))
B5: =IF(ISNUMBER(A5),TEXT(A5,"ddd"),"") | M5: =IF(OR(L5="",AND(E5<>"Up",E5<>"Down")),"",IF(OR(L5="In line",L5="Mixed"),"Neutral data",IF(OR(AND(L5="Hotter",E5="Down"),AND(L5="Cooler",E5="Up")),"With data","Against data"))) | V5: =IF(OR(AND(E5<>"Up",E5<>"Down"),NOT(ISNUMBER(S5)),IF(E5="Up",Q5,R5)=""),"",IF(S5>=100,"Back to open",IF(OR(IF(E5="Up",Q5,R5)="1-5 min",IF(E5="Up",Q5,R5)="5-15 min"),"Continued",IF(S5>=50,"Partial retrace","Stalled / chop")))) | W5: =IF(OR(Q5="",R5=""),"",IFERROR(IF(AND(Q5="Not by 16:00",R5="Not by 16:00"),"Neither taken",IF(FIND("|"&Q5&"|","|1-5 min|5-15 min|15-60 min|9:30-11:00|11:00-16:00|Not by 16:00|")=FIND("|"&R5&"|","|1-5 min|5-15 min|15-60 min|9:30-11:00|11:00-16:00|Not by 16:00|"),"Same window",IF(FIND("|"&Q5&"|","|1-5 min|5-15 min|15-60 min|9:30-11:00|11:00-16:00|Not by 16:00|")<FIND("|"&R5&"|","|1-5 min|5-15 min|15-60 min|9:30-11:00|11:00-16:00|Not by 16:00|"),IF(E5="Up","High first (main side)",IF(E5="Down","High first (wick side)","High first")),IF(E5="Down","Low first (main side)",IF(E5="Up","Low first (wick side)","Low first"))))),"Check entries"))
B6: =IF(ISNUMBER(A6),TEXT(A6,"ddd"),"") | M6: =IF(OR(L6="",AND(E6<>"Up",E6<>"Down")),"",IF(OR(L6="In line",L6="Mixed"),"Neutral data",IF(OR(AND(L6="Hotter",E6="Down"),AND(L6="Cooler",E6="Up")),"With data","Against data"))) | V6: =IF(OR(AND(E6<>"Up",E6<>"Down"),NOT(ISNUMBER(S6)),IF(E6="Up",Q6,R6)=""),"",IF(S6>=100,"Back to open",IF(OR(IF(E6="Up",Q6,R6)="1-5 min",IF(E6="Up",Q6,R6)="5-15 min"),"Continued",IF(S6>=50,"Partial retrace","Stalled / chop")))) | W6: =IF(OR(Q6="",R6=""),"",IFERROR(IF(AND(Q6="Not by 16:00",R6="Not by 16:00"),"Neither taken",IF(FIND("|"&Q6&"|","|1-5 min|5-15 min|15-60 min|9:30-11:00|11:00-16:00|Not by 16:00|")=FIND("|"&R6&"|","|1-5 min|5-15 min|15-60 min|9:30-11:00|11:00-16:00|Not by 16:00|"),"Same window",IF(FIND("|"&Q6&"|","|1-5 min|5-15 min|15-60 min|9:30-11:00|11:00-16:00|Not by 16:00|")<FIND("|"&R6&"|","|1-5 min|5-15 min|15-60 min|9:30-11:00|11:00-16:00|Not by 16:00|"),IF(E6="Up","High first (main side)",IF(E6="Down","High first (wick side)","High first")),IF(E6="Down","Low first (main side)",IF(E6="Up","Low first (wick side)","Low first"))))),"Check entries"))
B7: =IF(ISNUMBER(A7),TEXT(A7,"ddd"),"") | M7: =IF(OR(L7="",AND(E7<>"Up",E7<>"Down")),"",IF(OR(L7="In line",L7="Mixed"),"Neutral data",IF(OR(AND(L7="Hotter",E7="Down"),AND(L7="Cooler",E7="Up")),"With data","Against data"))) | V7: =IF(OR(AND(E7<>"Up",E7<>"Down"),NOT(ISNUMBER(S7)),IF(E7="Up",Q7,R7)=""),"",IF(S7>=100,"Back to open",IF(OR(IF(E7="Up",Q7,R7)="1-5 min",IF(E7="Up",Q7,R7)="5-15 min"),"Continued",IF(S7>=50,"Partial retrace","Stalled / chop")))) | W7: =IF(OR(Q7="",R7=""),"",IFERROR(IF(AND(Q7="Not by 16:00",R7="Not by 16:00"),"Neither taken",IF(FIND("|"&Q7&"|","|1-5 min|5-15 min|15-60 min|9:30-11:00|11:00-16:00|Not by 16:00|")=FIND("|"&R7&"|","|1-5 min|5-15 min|15-60 min|9:30-11:00|11:00-16:00|Not by 16:00|"),"Same window",IF(FIND("|"&Q7&"|","|1-5 min|5-15 min|15-60 min|9:30-11:00|11:00-16:00|Not by 16:00|")<FIND("|"&R7&"|","|1-5 min|5-15 min|15-60 min|9:30-11:00|11:00-16:00|Not by 16:00|"),IF(E7="Up","High first (main side)",IF(E7="Down","High first (wick side)","High first")),IF(E7="Down","Low first (main side)",IF(E7="Up","Low first (wick side)","Low first"))))),"Check entries"))
B8: =IF(ISNUMBER(A8),TEXT(A8,"ddd"),"") | M8: =IF(OR(L8="",AND(E8<>"Up",E8<>"Down")),"",IF(OR(L8="In line",L8="Mixed"),"Neutral data",IF(OR(AND(L8="Hotter",E8="Down"),AND(L8="Cooler",E8="Up")),"With data","Against data"))) | V8: =IF(OR(AND(E8<>"Up",E8<>"Down"),NOT(ISNUMBER(S8)),IF(E8="Up",Q8,R8)=""),"",IF(S8>=100,"Back to open",IF(OR(IF(E8="Up",Q8,R8)="1-5 min",IF(E8="Up",Q8,R8)="5-15 min"),"Continued",IF(S8>=50,"Partial retrace","Stalled / chop")))) | W8: =IF(OR(Q8="",R8=""),"",IFERROR(IF(AND(Q8="Not by 16:00",R8="Not by 16:00"),"Neither taken",IF(FIND("|"&Q8&"|","|1-5 min|5-15 min|15-60 min|9:30-11:00|11:00-16:00|Not by 16:00|")=FIND("|"&R8&"|","|1-5 min|5-15 min|15-60 min|9:30-11:00|11:00-16:00|Not by 16:00|"),"Same window",IF(FIND("|"&Q8&"|","|1-5 min|5-15 min|15-60 min|9:30-11:00|11:00-16:00|Not by 16:00|")<FIND("|"&R8&"|","|1-5 min|5-15 min|15-60 min|9:30-11:00|11:00-16:00|Not by 16:00|"),IF(E8="Up","High first (main side)",IF(E8="Down","High first (wick side)","High first")),IF(E8="Down","Low first (main side)",IF(E8="Up","Low first (wick side)","Low first"))))),"Check entries"))
B9: =IF(ISNUMBER(A9),TEXT(A9,"ddd"),"") | M9: =IF(OR(L9="",AND(E9<>"Up",E9<>"Down")),"",IF(OR(L9="In line",L9="Mixed"),"Neutral data",IF(OR(AND(L9="Hotter",E9="Down"),AND(L9="Cooler",E9="Up")),"With data","Against data"))) | V9: =IF(OR(AND(E9<>"Up",E9<>"Down"),NOT(ISNUMBER(S9)),IF(E9="Up",Q9,R9)=""),"",IF(S9>=100,"Back to open",IF(OR(IF(E9="Up",Q9,R9)="1-5 min",IF(E9="Up",Q9,R9)="5-15 min"),"Continued",IF(S9>=50,"Partial retrace","Stalled / chop")))) | W9: =IF(OR(Q9="",R9=""),"",IFERROR(IF(AND(Q9="Not by 16:00",R9="Not by 16:00"),"Neither taken",IF(FIND("|"&Q9&"|","|1-5 min|5-15 min|15-60 min|9:30-11:00|11:00-16:00|Not by 16:00|")=FIND("|"&R9&"|","|1-5 min|5-15 min|15-60 min|9:30-11:00|11:00-16:00|Not by 16:00|"),"Same window",IF(FIND("|"&Q9&"|","|1-5 min|5-15 min|15-60 min|9:30-11:00|11:00-16:00|Not by 16:00|")<FIND("|"&R9&"|","|1-5 min|5-15 min|15-60 min|9:30-11:00|11:00-16:00|Not by 16:00|"),IF(E9="Up","High first (main side)",IF(E9="Down","High first (wick side)","High first")),IF(E9="Down","Low first (main side)",IF(E9="Up","Low first (wick side)","Low first"))))),"Check entries"))
B10: =IF(ISNUMBER(A10),TEXT(A10,"ddd"),"") | M10: =IF(OR(L10="",AND(E10<>"Up",E10<>"Down")),"",IF(OR(L10="In line",L10="Mixed"),"Neutral data",IF(OR(AND(L10="Hotter",E10="Down"),AND(L10="Cooler",E10="Up")),"With data","Against data"))) | V10: =IF(OR(AND(E10<>"Up",E10<>"Down"),NOT(ISNUMBER(S10)),IF(E10="Up",Q10,R10)=""),"",IF(S10>=100,"Back to open",IF(OR(IF(E10="Up",Q10,R10)="1-5 min",IF(E10="Up",Q10,R10)="5-15 min"),"Continued",IF(S10>=50,"Partial retrace","Stalled / chop")))) | W10: =IF(OR(Q10="",R10=""),"",IFERROR(IF(AND(Q10="Not by 16:00",R10="Not by 16:00"),"Neither taken",IF(FIND("|"&Q10&"|","|1-5 min|5-15 min|15-60 min|9:30-11:00|11:00-16:00|Not by 16:00|")=FIND("|"&R10&"|","|1-5 min|5-15 min|15-60 min|9:30-11:00|11:00-16:00|Not by 16:00|"),"Same window",IF(FIND("|"&Q10&"|","|1-5 min|5-15 min|15-60 min|9:30-11:00|11:00-16:00|Not by 16:00|")<FIND("|"&R10&"|","|1-5 min|5-15 min|15-60 min|9:30-11:00|11:00-16:00|Not by 16:00|"),IF(E10="Up","High first (main side)",IF(E10="Down","High first (wick side)","High first")),IF(E10="Down","Low first (main side)",IF(E10="Up","Low first (wick side)","Low first"))))),"Check entries"))
B11: =IF(ISNUMBER(A11),TEXT(A11,"ddd"),"") | M11: =IF(OR(L11="",AND(E11<>"Up",E11<>"Down")),"",IF(OR(L11="In line",L11="Mixed"),"Neutral data",IF(OR(AND(L11="Hotter",E11="Down"),AND(L11="Cooler",E11="Up")),"With data","Against data"))) | V11: =IF(OR(AND(E11<>"Up",E11<>"Down"),NOT(ISNUMBER(S11)),IF(E11="Up",Q11,R11)=""),"",IF(S11>=100,"Back to open",IF(OR(IF(E11="Up",Q11,R11)="1-5 min",IF(E11="Up",Q11,R11)="5-15 min"),"Continued",IF(S11>=50,"Partial retrace","Stalled / chop")))) | W11: =IF(OR(Q11="",R11=""),"",IFERROR(IF(AND(Q11="Not by 16:00",R11="Not by 16:00"),"Neither taken",IF(FIND("|"&Q11&"|","|1-5 min|5-15 min|15-60 min|9:30-11:00|11:00-16:00|Not by 16:00|")=FIND("|"&R11&"|","|1-5 min|5-15 min|15-60 min|9:30-11:00|11:00-16:00|Not by 16:00|"),"Same window",IF(FIND("|"&Q11&"|","|1-5 min|5-15 min|15-60 min|9:30-11:00|11:00-16:00|Not by 16:00|")<FIND("|"&R11&"|","|1-5 min|5-15 min|15-60 min|9:30-11:00|11:00-16:00|Not by 16:00|"),IF(E11="Up","High first (main side)",IF(E11="Down","High first (wick side)","High first")),IF(E11="Down","Low first (main side)",IF(E11="Up","Low first (wick side)","Low first"))))),"Check entries"))
B12: =IF(ISNUMBER(A12),TEXT(A12,"ddd"),"") | M12: =IF(OR(L12="",AND(E12<>"Up",E12<>"Down")),"",IF(OR(L12="In line",L12="Mixed"),"Neutral data",IF(OR(AND(L12="Hotter",E12="Down"),AND(L12="Cooler",E12="Up")),"With data","Against data"))) | V12: =IF(OR(AND(E12<>"Up",E12<>"Down"),NOT(ISNUMBER(S12)),IF(E12="Up",Q12,R12)=""),"",IF(S12>=100,"Back to open",IF(OR(IF(E12="Up",Q12,R12)="1-5 min",IF(E12="Up",Q12,R12)="5-15 min"),"Continued",IF(S12>=50,"Partial retrace","Stalled / chop")))) | W12: =IF(OR(Q12="",R12=""),"",IFERROR(IF(AND(Q12="Not by 16:00",R12="Not by 16:00"),"Neither taken",IF(FIND("|"&Q12&"|","|1-5 min|5-15 min|15-60 min|9:30-11:00|11:00-16:00|Not by 16:00|")=FIND("|"&R12&"|","|1-5 min|5-15 min|15-60 min|9:30-11:00|11:00-16:00|Not by 16:00|"),"Same window",IF(FIND("|"&Q12&"|","|1-5 min|5-15 min|15-60 min|9:30-11:00|11:00-16:00|Not by 16:00|")<FIND("|"&R12&"|","|1-5 min|5-15 min|15-60 min|9:30-11:00|11:00-16:00|Not by 16:00|"),IF(E12="Up","High first (main side)",IF(E12="Down","High first (wick side)","High first")),IF(E12="Down","Low first (main side)",IF(E12="Up","Low first (wick side)","Low first"))))),"Check entries"))
B13: =IF(ISNUMBER(A13),TEXT(A13,"ddd"),"") | M13: =IF(OR(L13="",AND(E13<>"Up",E13<>"Down")),"",IF(OR(L13="In line",L13="Mixed"),"Neutral data",IF(OR(AND(L13="Hotter",E13="Down"),AND(L13="Cooler",E13="Up")),"With data","Against data"))) | V13: =IF(OR(AND(E13<>"Up",E13<>"Down"),NOT(ISNUMBER(S13)),IF(E13="Up",Q13,R13)=""),"",IF(S13>=100,"Back to open",IF(OR(IF(E13="Up",Q13,R13)="1-5 min",IF(E13="Up",Q13,R13)="5-15 min"),"Continued",IF(S13>=50,"Partial retrace","Stalled / chop")))) | W13: =IF(OR(Q13="",R13=""),"",IFERROR(IF(AND(Q13="Not by 16:00",R13="Not by 16:00"),"Neither taken",IF(FIND("|"&Q13&"|","|1-5 min|5-15 min|15-60 min|9:30-11:00|11:00-16:00|Not by 16:00|")=FIND("|"&R13&"|","|1-5 min|5-15 min|15-60 min|9:30-11:00|11:00-16:00|Not by 16:00|"),"Same window",IF(FIND("|"&Q13&"|","|1-5 min|5-15 min|15-60 min|9:30-11:00|11:00-16:00|Not by 16:00|")<FIND("|"&R13&"|","|1-5 min|5-15 min|15-60 min|9:30-11:00|11:00-16:00|Not by 16:00|"),IF(E13="Up","High first (main side)",IF(E13="Down","High first (wick side)","High first")),IF(E13="Down","Low first (main side)",IF(E13="Up","Low first (wick side)","Low first"))))),"Check entries"))
B14: =IF(ISNUMBER(A14),TEXT(A14,"ddd"),"") | M14: =IF(OR(L14="",AND(E14<>"Up",E14<>"Down")),"",IF(OR(L14="In line",L14="Mixed"),"Neutral data",IF(OR(AND(L14="Hotter",E14="Down"),AND(L14="Cooler",E14="Up")),"With data","Against data"))) | V14: =IF(OR(AND(E14<>"Up",E14<>"Down"),NOT(ISNUMBER(S14)),IF(E14="Up",Q14,R14)=""),"",IF(S14>=100,"Back to open",IF(OR(IF(E14="Up",Q14,R14)="1-5 min",IF(E14="Up",Q14,R14)="5-15 min"),"Continued",IF(S14>=50,"Partial retrace","Stalled / chop")))) | W14: =IF(OR(Q14="",R14=""),"",IFERROR(IF(AND(Q14="Not by 16:00",R14="Not by 16:00"),"Neither taken",IF(FIND("|"&Q14&"|","|1-5 min|5-15 min|15-60 min|9:30-11:00|11:00-16:00|Not by 16:00|")=FIND("|"&R14&"|","|1-5 min|5-15 min|15-60 min|9:30-11:00|11:00-16:00|Not by 16:00|"),"Same window",IF(FIND("|"&Q14&"|","|1-5 min|5-15 min|15-60 min|9:30-11:00|11:00-16:00|Not by 16:00|")<FIND("|"&R14&"|","|1-5 min|5-15 min|15-60 min|9:30-11:00|11:00-16:00|Not by 16:00|"),IF(E14="Up","High first (main side)",IF(E14="Down","High first (wick side)","High first")),IF(E14="Down","Low first (main side)",IF(E14="Up","Low first (wick side)","Low first"))))),"Check entries"))
B15: =IF(ISNUMBER(A15),TEXT(A15,"ddd"),"") | M15: =IF(OR(L15="",AND(E15<>"Up",E15<>"Down")),"",IF(OR(L15="In line",L15="Mixed"),"Neutral data",IF(OR(AND(L15="Hotter",E15="Down"),AND(L15="Cooler",E15="Up")),"With data","Against data"))) | V15: =IF(OR(AND(E15<>"Up",E15<>"Down"),NOT(ISNUMBER(S15)),IF(E15="Up",Q15,R15)=""),"",IF(S15>=100,"Back to open",IF(OR(IF(E15="Up",Q15,R15)="1-5 min",IF(E15="Up",Q15,R15)="5-15 min"),"Continued",IF(S15>=50,"Partial retrace","Stalled / chop")))) | W15: =IF(OR(Q15="",R15=""),"",IFERROR(IF(AND(Q15="Not by 16:00",R15="Not by 16:00"),"Neither taken",IF(FIND("|"&Q15&"|","|1-5 min|5-15 min|15-60 min|9:30-11:00|11:00-16:00|Not by 16:00|")=FIND("|"&R15&"|","|1-5 min|5-15 min|15-60 min|9:30-11:00|11:00-16:00|Not by 16:00|"),"Same window",IF(FIND("|"&Q15&"|","|1-5 min|5-15 min|15-60 min|9:30-11:00|11:00-16:00|Not by 16:00|")<FIND("|"&R15&"|","|1-5 min|5-15 min|15-60 min|9:30-11:00|11:00-16:00|Not by 16:00|"),IF(E15="Up","High first (main side)",IF(E15="Down","High first (wick side)","High first")),IF(E15="Down","Low first (main side)",IF(E15="Up","Low first (wick side)","Low first"))))),"Check entries"))
... B503: =IF(ISNUMBER(A503),TEXT(A503,"ddd"),"") | M503: =IF(OR(L503="",AND(E503<>"Up",E503<>"Down")),"",IF(OR(L503="In line",L503="Mixed"),"Neutral data",IF(OR(AND(L503="Hotter",E503="Down"),AND(L503="Cooler",E503="Up")),"With data","Against data"))) | V503: =IF(OR(AND(E503<>"Up",E503<>"Down"),NOT(ISNUMBER(S503)),IF(E503="Up",Q503,R503)=""),"",IF(S503>=100,"Back to open",IF(OR(IF(E503="Up",Q503,R503)="1-5 min",IF(E503="Up",Q503,R503)="5-15 min"),"Continued",IF(S503>=50,"Partial retrace","Stalled / chop")))) | W503: =IF(OR(Q503="",R503=""),"",IFERROR(IF(AND(Q503="Not by 16:00",R503="Not by 16:00"),"Neither taken",IF(FIND("|"&Q503&"|","|1-5 min|5-15 min|15-60 min|9:30-11:00|11:00-16:00|Not by 16:00|")=FIND("|"&R503&"|","|1-5 min|5-15 min|15-60 min|9:30-11:00|11:00-16:00|Not by 16:00|"),"Same window",IF(FIND("|"&Q503&"|","|1-5 min|5-15 min|15-60 min|9:30-11:00|11:00-16:00|Not by 16:00|")<FIND("|"&R503&"|","|1-5 min|5-15 min|15-60 min|9:30-11:00|11:00-16:00|Not by 16:00|"),IF(E503="Up","High first (main side)",IF(E503="Down","High first (wick side)","High first")),IF(E503="Down","Low first (main side)",IF(E503="Up","Low first (wick side)","Low first"))))),"Check entries"))

Sheet Stats
A1: CPI $NQ – STATS (updates automatically from the CPI Log tab)
A2: Only rows you have filled are counted. '–' = no data yet. Small samples lie: look at n before trusting a %.
A3: Count releases from | C3: 43831 | D3: to | E3: =TODAY() | F3: ← change these dates to test a period (e.g. 2023 onwards)
A4: Releases in this period | C4: =COUNTIFS('CPI Log'!$A$4:$A$1000,">="&$C$3,'CPI Log'!$A$4:$A$1000,"<="&$E$3) | D4: with an Outcome: | E4: =COUNTIFS('CPI Log'!$A$4:$A$1000,">="&$C$3,'CPI Log'!$A$4:$A$1000,"<="&$E$3,'CPI Log'!$V$4:$V$1000,"Continued")+COUNTIFS('CPI Log'!$A$4:$A$1000,">="&$C$3,'CPI Log'!$A$4:$A$1000,"<="&$E$3,'CPI Log'!$V$4:$V$1000,"Back to open")+COUNTIFS('CPI Log'!$A$4:$A$1000,">="&$C$3,'CPI Log'!$A$4:$A$1000,"<="&$E$3,'CPI Log'!$V$4:$V$1000,"Partial retrace")+COUNTIFS('CPI Log'!$A$4:$A$1000,">="&$C$3,'CPI Log'!$A$4:$A$1000,"<="&$E$3,'CPI Log'!$V$4:$V$1000,"Stalled / chop")
A6: 1 · What did the main move do after the 1st minute? (Outcome 8:31–8:45)
A7: Read across: e.g. 'when CPI was Hotter, the main move went back to the 8:30 open X% of the time'.
A8: Outcome | B8: All | C8: Hotter | D8: Cooler | E8: In line | F8: Mixed
A9: Continued | B9: =IFERROR((COUNTIFS('CPI Log'!$A$4:$A$1000,">="&$C$3,'CPI Log'!$A$4:$A$1000,"<="&$E$3,'CPI Log'!$V$4:$V$1000,$A9))/(B$13),"–") | C9: =IFERROR((COUNTIFS('CPI Log'!$A$4:$A$1000,">="&$C$3,'CPI Log'!$A$4:$A$1000,"<="&$E$3,'CPI Log'!$V$4:$V$1000,$A9,'CPI Log'!$L$4:$L$1000,"Hotter"))/(C$13),"–") | D9: =IFERROR((COUNTIFS('CPI Log'!$A$4:$A$1000,">="&$C$3,'CPI Log'!$A$4:$A$1000,"<="&$E$3,'CPI Log'!$V$4:$V$1000,$A9,'CPI Log'!$L$4:$L$1000,"Cooler"))/(D$13),"–") | E9: =IFERROR((COUNTIFS('CPI Log'!$A$4:$A$1000,">="&$C$3,'CPI Log'!$A$4:$A$1000,"<="&$E$3,'CPI Log'!$V$4:$V$1000,$A9,'CPI Log'!$L$4:$L$1000,"In line"))/(E$13),"–") | F9: =IFERROR((COUNTIFS('CPI Log'!$A$4:$A$1000,">="&$C$3,'CPI Log'!$A$4:$A$1000,"<="&$E$3,'CPI Log'!$V$4:$V$1000,$A9,'CPI Log'!$L$4:$L$1000,"Mixed"))/(F$13),"–")
A10: Back to open | B10: =IFERROR((COUNTIFS('CPI Log'!$A$4:$A$1000,">="&$C$3,'CPI Log'!$A$4:$A$1000,"<="&$E$3,'CPI Log'!$V$4:$V$1000,$A10))/(B$13),"–") | C10: =IFERROR((COUNTIFS('CPI Log'!$A$4:$A$1000,">="&$C$3,'CPI Log'!$A$4:$A$1000,"<="&$E$3,'CPI Log'!$V$4:$V$1000,$A10,'CPI Log'!$L$4:$L$1000,"Hotter"))/(C$13),"–") | D10: =IFERROR((COUNTIFS('CPI Log'!$A$4:$A$1000,">="&$C$3,'CPI Log'!$A$4:$A$1000,"<="&$E$3,'CPI Log'!$V$4:$V$1000,$A10,'CPI Log'!$L$4:$L$1000,"Cooler"))/(D$13),"–") | E10: =IFERROR((COUNTIFS('CPI Log'!$A$4:$A$1000,">="&$C$3,'CPI Log'!$A$4:$A$1000,"<="&$E$3,'CPI Log'!$V$4:$V$1000,$A10,'CPI Log'!$L$4:$L$1000,"In line"))/(E$13),"–") | F10: =IFERROR((COUNTIFS('CPI Log'!$A$4:$A$1000,">="&$C$3,'CPI Log'!$A$4:$A$1000,"<="&$E$3,'CPI Log'!$V$4:$V$1000,$A10,'CPI Log'!$L$4:$L$1000,"Mixed"))/(F$13),"–")
A11: Partial retrace | B11: =IFERROR((COUNTIFS('CPI Log'!$A$4:$A$1000,">="&$C$3,'CPI Log'!$A$4:$A$1000,"<="&$E$3,'CPI Log'!$V$4:$V$1000,$A11))/(B$13),"–") | C11: =IFERROR((COUNTIFS('CPI Log'!$A$4:$A$1000,">="&$C$3,'CPI Log'!$A$4:$A$1000,"<="&$E$3,'CPI Log'!$V$4:$V$1000,$A11,'CPI Log'!$L$4:$L$1000,"Hotter"))/(C$13),"–") | D11: =IFERROR((COUNTIFS('CPI Log'!$A$4:$A$1000,">="&$C$3,'CPI Log'!$A$4:$A$1000,"<="&$E$3,'CPI Log'!$V$4:$V$1000,$A11,'CPI Log'!$L$4:$L$1000,"Cooler"))/(D$13),"–") | E11: =IFERROR((COUNTIFS('CPI Log'!$A$4:$A$1000,">="&$C$3,'CPI Log'!$A$4:$A$1000,"<="&$E$3,'CPI Log'!$V$4:$V$1000,$A11,'CPI Log'!$L$4:$L$1000,"In line"))/(E$13),"–") | F11: =IFERROR((COUNTIFS('CPI Log'!$A$4:$A$1000,">="&$C$3,'CPI Log'!$A$4:$A$1000,"<="&$E$3,'CPI Log'!$V$4:$V$1000,$A11,'CPI Log'!$L$4:$L$1000,"Mixed"))/(F$13),"–")
A12: Stalled / chop | B12: =IFERROR((COUNTIFS('CPI Log'!$A$4:$A$1000,">="&$C$3,'CPI Log'!$A$4:$A$1000,"<="&$E$3,'CPI Log'!$V$4:$V$1000,$A12))/(B$13),"–") | C12: =IFERROR((COUNTIFS('CPI Log'!$A$4:$A$1000,">="&$C$3,'CPI Log'!$A$4:$A$1000,"<="&$E$3,'CPI Log'!$V$4:$V$1000,$A12,'CPI Log'!$L$4:$L$1000,"Hotter"))/(C$13),"–") | D12: =IFERROR((COUNTIFS('CPI Log'!$A$4:$A$1000,">="&$C$3,'CPI Log'!$A$4:$A$1000,"<="&$E$3,'CPI Log'!$V$4:$V$1000,$A12,'CPI Log'!$L$4:$L$1000,"Cooler"))/(D$13),"–") | E12: =IFERROR((COUNTIFS('CPI Log'!$A$4:$A$1000,">="&$C$3,'CPI Log'!$A$4:$A$1000,"<="&$E$3,'CPI Log'!$V$4:$V$1000,$A12,'CPI Log'!$L$4:$L$1000,"In line"))/(E$13),"–") | F12: =IFERROR((COUNTIFS('CPI Log'!$A$4:$A$1000,">="&$C$3,'CPI Log'!$A$4:$A$1000,"<="&$E$3,'CPI Log'!$V$4:$V$1000,$A12,'CPI Log'!$L$4:$L$1000,"Mixed"))/(F$13),"–")
A13: n (releases) | B13: =COUNTIFS('CPI Log'!$A$4:$A$1000,">="&$C$3,'CPI Log'!$A$4:$A$1000,"<="&$E$3,'CPI Log'!$V$4:$V$1000,"Continued")+COUNTIFS('CPI Log'!$A$4:$A$1000,">="&$C$3,'CPI Log'!$A$4:$A$1000,"<="&$E$3,'CPI Log'!$V$4:$V$1000,"Back to open")+COUNTIFS('CPI Log'!$A$4:$A$1000,">="&$C$3,'CPI Log'!$A$4:$A$1000,"<="&$E$3,'CPI Log'!$V$4:$V$1000,"Partial retrace")+COUNTIFS('CPI Log'!$A$4:$A$1000,">="&$C$3,'CPI Log'!$A$4:$A$1000,"<="&$E$3,'CPI Log'!$V$4:$V$1000,"Stalled / chop") | C13: =COUNTIFS('CPI Log'!$A$4:$A$1000,">="&$C$3,'CPI Log'!$A$4:$A$1000,"<="&$E$3,'CPI Log'!$V$4:$V$1000,"Continued",'CPI Log'!$L$4:$L$1000,"Hotter")+COUNTIFS('CPI Log'!$A$4:$A$1000,">="&$C$3,'CPI Log'!$A$4:$A$1000,"<="&$E$3,'CPI Log'!$V$4:$V$1000,"Back to open",'CPI Log'!$L$4:$L$1000,"Hotter")+COUNTIFS('CPI Log'!$A$4:$A$1000,">="&$C$3,'CPI Log'!$A$4:$A$1000,"<="&$E$3,'CPI Log'!$V$4:$V$1000,"Partial retrace",'CPI Log'!$L$4:$L$1000,"Hotter")+COUNTIFS('CPI Log'!$A$4:$A$1000,">="&$C$3,'CPI Log'!$A$4:$A$1000,"<="&$E$3,'CPI Log'!$V$4:$V$1000,"Stalled / chop",'CPI Log'!$L$4:$L$1000,"Hotter") | D13: =COUNTIFS('CPI Log'!$A$4:$A$1000,">="&$C$3,'CPI Log'!$A$4:$A$1000,"<="&$E$3,'CPI Log'!$V$4:$V$1000,"Continued",'CPI Log'!$L$4:$L$1000,"Cooler")+COUNTIFS('CPI Log'!$A$4:$A$1000,">="&$C$3,'CPI Log'!$A$4:$A$1000,"<="&$E$3,'CPI Log'!$V$4:$V$1000,"Back to open",'CPI Log'!$L$4:$L$1000,"Cooler")+COUNTIFS('CPI Log'!$A$4:$A$1000,">="&$C$3,'CPI Log'!$A$4:$A$1000,"<="&$E$3,'CPI Log'!$V$4:$V$1000,"Partial retrace",'CPI Log'!$L$4:$L$1000,"Cooler")+COUNTIFS('CPI Log'!$A$4:$A$1000,">="&$C$3,'CPI Log'!$A$4:$A$1000,"<="&$E$3,'CPI Log'!$V$4:$V$1000,"Stalled / chop",'CPI Log'!$L$4:$L$1000,"Cooler") | E13: =COUNTIFS('CPI Log'!$A$4:$A$1000,">="&$C$3,'CPI Log'!$A$4:$A$1000,"<="&$E$3,'CPI Log'!$V$4:$V$1000,"Continued",'CPI Log'!$L$4:$L$1000,"In line")+COUNTIFS('CPI Log'!$A$4:$A$1000,">="&$C$3,'CPI Log'!$A$4:$A$1000,"<="&$E$3,'CPI Log'!$V$4:$V$1000,"Back to open",'CPI Log'!$L$4:$L$1000,"In line")+COUNTIFS('CPI Log'!$A$4:$A$1000,">="&$C$3,'CPI Log'!$A$4:$A$1000,"<="&$E$3,'CPI Log'!$V$4:$V$1000,"Partial retrace",'CPI Log'!$L$4:$L$1000,"In line")+COUNTIFS('CPI Log'!$A$4:$A$1000,">="&$C$3,'CPI Log'!$A$4:$A$1000,"<="&$E$3,'CPI Log'!$V$4:$V$1000,"Stalled / chop",'CPI Log'!$L$4:$L$1000,"In line") | F13: =COUNTIFS('CPI Log'!$A$4:$A$1000,">="&$C$3,'CPI Log'!$A$4:$A$1000,"<="&$E$3,'CPI Log'!$V$4:$V$1000,"Continued",'CPI Log'!$L$4:$L$1000,"Mixed")+COUNTIFS('CPI Log'!$A$4:$A$1000,">="&$C$3,'CPI Log'!$A$4:$A$1000,"<="&$E$3,'CPI Log'!$V$4:$V$1000,"Back to open",'CPI Log'!$L$4:$L$1000,"Mixed")+COUNTIFS('CPI Log'!$A$4:$A$1000,">="&$C$3,'CPI Log'!$A$4:$A$1000,"<="&$E$3,'CPI Log'!$V$4:$V$1000,"Partial retrace",'CPI Log'!$L$4:$L$1000,"Mixed")+COUNTIFS('CPI Log'!$A$4:$A$1000,">="&$C$3,'CPI Log'!$A$4:$A$1000,"<="&$E$3,'CPI Log'!$V$4:$V$1000,"Stalled / chop",'CPI Log'!$L$4:$L$1000,"Mixed")
A16: 2 · When did price come back to the 8:30 open?
A17: Cumulative % = it had come back by the end of that window.
A18: Window (NY time) | B18: # | C18: % | D18: Cumulative %
A19: 0-15 sec | B19: =COUNTIFS('CPI Log'!$A$4:$A$1000,">="&$C$3,'CPI Log'!$A$4:$A$1000,"<="&$E$3,'CPI Log'!$T$4:$T$1000,$A19) | C19: =IFERROR(B19/B$28,"–") | D19: =IFERROR(SUM(B$19:B19)/B$28,"–")
A20: 15-30 sec | B20: =COUNTIFS('CPI Log'!$A$4:$A$1000,">="&$C$3,'CPI Log'!$A$4:$A$1000,"<="&$E$3,'CPI Log'!$T$4:$T$1000,$A20) | C20: =IFERROR(B20/B$28,"–") | D20: =IFERROR(SUM(B$19:B20)/B$28,"–")
A21: 30-60 sec | B21: =COUNTIFS('CPI Log'!$A$4:$A$1000,">="&$C$3,'CPI Log'!$A$4:$A$1000,"<="&$E$3,'CPI Log'!$T$4:$T$1000,$A21) | C21: =IFERROR(B21/B$28,"–") | D21: =IFERROR(SUM(B$19:B21)/B$28,"–")
A22: 1-5 min | B22: =COUNTIFS('CPI Log'!$A$4:$A$1000,">="&$C$3,'CPI Log'!$A$4:$A$1000,"<="&$E$3,'CPI Log'!$T$4:$T$1000,$A22) | C22: =IFERROR(B22/B$28,"–") | D22: =IFERROR(SUM(B$19:B22)/B$28,"–")
A23: 5-15 min | B23: =COUNTIFS('CPI Log'!$A$4:$A$1000,">="&$C$3,'CPI Log'!$A$4:$A$1000,"<="&$E$3,'CPI Log'!$T$4:$T$1000,$A23) | C23: =IFERROR(B23/B$28,"–") | D23: =IFERROR(SUM(B$19:B23)/B$28,"–")
A24: 15-60 min | B24: =COUNTIFS('CPI Log'!$A$4:$A$1000,">="&$C$3,'CPI Log'!$A$4:$A$1000,"<="&$E$3,'CPI Log'!$T$4:$T$1000,$A24) | C24: =IFERROR(B24/B$28,"–") | D24: =IFERROR(SUM(B$19:B24)/B$28,"–")
A25: 9:30-11:00 | B25: =COUNTIFS('CPI Log'!$A$4:$A$1000,">="&$C$3,'CPI Log'!$A$4:$A$1000,"<="&$E$3,'CPI Log'!$T$4:$T$1000,$A25) | C25: =IFERROR(B25/B$28,"–") | D25: =IFERROR(SUM(B$19:B25)/B$28,"–")
A26: 11:00-16:00 | B26: =COUNTIFS('CPI Log'!$A$4:$A$1000,">="&$C$3,'CPI Log'!$A$4:$A$1000,"<="&$E$3,'CPI Log'!$T$4:$T$1000,$A26) | C26: =IFERROR(B26/B$28,"–") | D26: =IFERROR(SUM(B$19:B26)/B$28,"–")
A27: Not by 16:00 | B27: =COUNTIFS('CPI Log'!$A$4:$A$1000,">="&$C$3,'CPI Log'!$A$4:$A$1000,"<="&$E$3,'CPI Log'!$T$4:$T$1000,$A27) | C27: =IFERROR(B27/B$28,"–")
A28: n (releases) | B28: =SUM(B19:B27)
A31: 3 · At the 8:30 open, price… (does it just grab the liquidity and keep going?)
A32: Reaction | B32: # | C32: % | D32: % of the times it came back
A33: Swept & resumed | B33: =COUNTIFS('CPI Log'!$A$4:$A$1000,">="&$C$3,'CPI Log'!$A$4:$A$1000,"<="&$E$3,'CPI Log'!$U$4:$U$1000,$A33) | C33: =IFERROR(B33/B$37,"–") | D33: =IFERROR(B33/SUM(B$33:B$35),"–")
A34: Broke through | B34: =COUNTIFS('CPI Log'!$A$4:$A$1000,">="&$C$3,'CPI Log'!$A$4:$A$1000,"<="&$E$3,'CPI Log'!$U$4:$U$1000,$A34) | C34: =IFERROR(B34/B$37,"–") | D34: =IFERROR(B34/SUM(B$33:B$35),"–")
A35: Chopped around | B35: =COUNTIFS('CPI Log'!$A$4:$A$1000,">="&$C$3,'CPI Log'!$A$4:$A$1000,"<="&$E$3,'CPI Log'!$U$4:$U$1000,$A35) | C35: =IFERROR(B35/B$37,"–") | D35: =IFERROR(B35/SUM(B$33:B$35),"–")
A36: Never came back | B36: =COUNTIFS('CPI Log'!$A$4:$A$1000,">="&$C$3,'CPI Log'!$A$4:$A$1000,"<="&$E$3,'CPI Log'!$U$4:$U$1000,$A36) | C36: =IFERROR(B36/B$37,"–")
A37: n (releases) | B37: =SUM(B33:B36)
A40: 4 · How long until the 1-min candle's HIGH / LOW (BSL / SSL) got taken?
A41: Main side = the end of the 1-min candle in the Main Move direction (the HIGH when Main Move is Up). Wick side = the other end. Cumulative % = taken by the end of that window. 'Not by 16:00' = that end held as the high/low for the rest of the day.
A42: Window (NY time) | B42: Main side # | C42: Main side cum. % | D42: Wick side # | E42: Wick side cum. %
A43: 1-5 min | B43: =COUNTIFS('CPI Log'!$A$4:$A$1000,">="&$C$3,'CPI Log'!$A$4:$A$1000,"<="&$E$3,'CPI Log'!$E$4:$E$1000,"Up",'CPI Log'!$Q$4:$Q$1000,$A43)+COUNTIFS('CPI Log'!$A$4:$A$1000,">="&$C$3,'CPI Log'!$A$4:$A$1000,"<="&$E$3,'CPI Log'!$E$4:$E$1000,"Down",'CPI Log'!$R$4:$R$1000,$A43) | C43: =IFERROR(SUM(B$43:B43)/B$49,"–") | D43: =COUNTIFS('CPI Log'!$A$4:$A$1000,">="&$C$3,'CPI Log'!$A$4:$A$1000,"<="&$E$3,'CPI Log'!$E$4:$E$1000,"Up",'CPI Log'!$R$4:$R$1000,$A43)+COUNTIFS('CPI Log'!$A$4:$A$1000,">="&$C$3,'CPI Log'!$A$4:$A$1000,"<="&$E$3,'CPI Log'!$E$4:$E$1000,"Down",'CPI Log'!$Q$4:$Q$1000,$A43) | E43: =IFERROR(SUM(D$43:D43)/D$49,"–")
A44: 5-15 min | B44: =COUNTIFS('CPI Log'!$A$4:$A$1000,">="&$C$3,'CPI Log'!$A$4:$A$1000,"<="&$E$3,'CPI Log'!$E$4:$E$1000,"Up",'CPI Log'!$Q$4:$Q$1000,$A44)+COUNTIFS('CPI Log'!$A$4:$A$1000,">="&$C$3,'CPI Log'!$A$4:$A$1000,"<="&$E$3,'CPI Log'!$E$4:$E$1000,"Down",'CPI Log'!$R$4:$R$1000,$A44) | C44: =IFERROR(SUM(B$43:B44)/B$49,"–") | D44: =COUNTIFS('CPI Log'!$A$4:$A$1000,">="&$C$3,'CPI Log'!$A$4:$A$1000,"<="&$E$3,'CPI Log'!$E$4:$E$1000,"Up",'CPI Log'!$R$4:$R$1000,$A44)+COUNTIFS('CPI Log'!$A$4:$A$1000,">="&$C$3,'CPI Log'!$A$4:$A$1000,"<="&$E$3,'CPI Log'!$E$4:$E$1000,"Down",'CPI Log'!$Q$4:$Q$1000,$A44) | E44: =IFERROR(SUM(D$43:D44)/D$49,"–")
A45: 15-60 min | B45: =COUNTIFS('CPI Log'!$A$4:$A$1000,">="&$C$3,'CPI Log'!$A$4:$A$1000,"<="&$E$3,'CPI Log'!$E$4:$E$1000,"Up",'CPI Log'!$Q$4:$Q$1000,$A45)+COUNTIFS('CPI Log'!$A$4:$A$1000,">="&$C$3,'CPI Log'!$A$4:$A$1000,"<="&$E$3,'CPI Log'!$E$4:$E$1000,"Down",'CPI Log'!$R$4:$R$1000,$A45) | C45: =IFERROR(SUM(B$43:B45)/B$49,"–") | D45: =COUNTIFS('CPI Log'!$A$4:$A$1000,">="&$C$3,'CPI Log'!$A$4:$A$1000,"<="&$E$3,'CPI Log'!$E$4:$E$1000,"Up",'CPI Log'!$R$4:$R$1000,$A45)+COUNTIFS('CPI Log'!$A$4:$A$1000,">="&$C$3,'CPI Log'!$A$4:$A$1000,"<="&$E$3,'CPI Log'!$E$4:$E$1000,"Down",'CPI Log'!$Q$4:$Q$1000,$A45) | E45: =IFERROR(SUM(D$43:D45)/D$49,"–")
A46: 9:30-11:00 | B46: =COUNTIFS('CPI Log'!$A$4:$A$1000,">="&$C$3,'CPI Log'!$A$4:$A$1000,"<="&$E$3,'CPI Log'!$E$4:$E$1000,"Up",'CPI Log'!$Q$4:$Q$1000,$A46)+COUNTIFS('CPI Log'!$A$4:$A$1000,">="&$C$3,'CPI Log'!$A$4:$A$1000,"<="&$E$3,'CPI Log'!$E$4:$E$1000,"Down",'CPI Log'!$R$4:$R$1000,$A46) | C46: =IFERROR(SUM(B$43:B46)/B$49,"–") | D46: =COUNTIFS('CPI Log'!$A$4:$A$1000,">="&$C$3,'CPI Log'!$A$4:$A$1000,"<="&$E$3,'CPI Log'!$E$4:$E$1000,"Up",'CPI Log'!$R$4:$R$1000,$A46)+COUNTIFS('CPI Log'!$A$4:$A$1000,">="&$C$3,'CPI Log'!$A$4:$A$1000,"<="&$E$3,'CPI Log'!$E$4:$E$1000,"Down",'CPI Log'!$Q$4:$Q$1000,$A46) | E46: =IFERROR(SUM(D$43:D46)/D$49,"–")
A47: 11:00-16:00 | B47: =COUNTIFS('CPI Log'!$A$4:$A$1000,">="&$C$3,'CPI Log'!$A$4:$A$1000,"<="&$E$3,'CPI Log'!$E$4:$E$1000,"Up",'CPI Log'!$Q$4:$Q$1000,$A47)+COUNTIFS('CPI Log'!$A$4:$A$1000,">="&$C$3,'CPI Log'!$A$4:$A$1000,"<="&$E$3,'CPI Log'!$E$4:$E$1000,"Down",'CPI Log'!$R$4:$R$1000,$A47) | C47: =IFERROR(SUM(B$43:B47)/B$49,"–") | D47: =COUNTIFS('CPI Log'!$A$4:$A$1000,">="&$C$3,'CPI Log'!$A$4:$A$1000,"<="&$E$3,'CPI Log'!$E$4:$E$1000,"Up",'CPI Log'!$R$4:$R$1000,$A47)+COUNTIFS('CPI Log'!$A$4:$A$1000,">="&$C$3,'CPI Log'!$A$4:$A$1000,"<="&$E$3,'CPI Log'!$E$4:$E$1000,"Down",'CPI Log'!$Q$4:$Q$1000,$A47) | E47: =IFERROR(SUM(D$43:D47)/D$49,"–")
A48: Not by 16:00 | B48: =COUNTIFS('CPI Log'!$A$4:$A$1000,">="&$C$3,'CPI Log'!$A$4:$A$1000,"<="&$E$3,'CPI Log'!$E$4:$E$1000,"Up",'CPI Log'!$Q$4:$Q$1000,$A48)+COUNTIFS('CPI Log'!$A$4:$A$1000,">="&$C$3,'CPI Log'!$A$4:$A$1000,"<="&$E$3,'CPI Log'!$E$4:$E$1000,"Down",'CPI Log'!$R$4:$R$1000,$A48) | D48: =COUNTIFS('CPI Log'!$A$4:$A$1000,">="&$C$3,'CPI Log'!$A$4:$A$1000,"<="&$E$3,'CPI Log'!$E$4:$E$1000,"Up",'CPI Log'!$R$4:$R$1000,$A48)+COUNTIFS('CPI Log'!$A$4:$A$1000,">="&$C$3,'CPI Log'!$A$4:$A$1000,"<="&$E$3,'CPI Log'!$E$4:$E$1000,"Down",'CPI Log'!$Q$4:$Q$1000,$A48)
A49: n (releases) | B49: =SUM(B43:B48) | D49: =SUM(D43:D48)
A51: Which side was taken first? | B51: # | C51: %
A52: Main side first (continuation) | B52: =COUNTIFS('CPI Log'!$A$4:$A$1000,">="&$C$3,'CPI Log'!$A$4:$A$1000,"<="&$E$3,'CPI Log'!$W$4:$W$1000,"High first (main side)")+COUNTIFS('CPI Log'!$A$4:$A$1000,">="&$C$3,'CPI Log'!$A$4:$A$1000,"<="&$E$3,'CPI Log'!$W$4:$W$1000,"Low first (main side)") | C52: =IFERROR(B52/B$56,"–")
A53: Wick side first (reversal) | B53: =COUNTIFS('CPI Log'!$A$4:$A$1000,">="&$C$3,'CPI Log'!$A$4:$A$1000,"<="&$E$3,'CPI Log'!$W$4:$W$1000,"High first (wick side)")+COUNTIFS('CPI Log'!$A$4:$A$1000,">="&$C$3,'CPI Log'!$A$4:$A$1000,"<="&$E$3,'CPI Log'!$W$4:$W$1000,"Low first (wick side)") | C53: =IFERROR(B53/B$56,"–")
A54: Both in the same window | B54: =COUNTIFS('CPI Log'!$A$4:$A$1000,">="&$C$3,'CPI Log'!$A$4:$A$1000,"<="&$E$3,'CPI Log'!$W$4:$W$1000,"Same window") | C54: =IFERROR(B54/B$56,"–")
A55: Neither taken by 16:00 | B55: =COUNTIFS('CPI Log'!$A$4:$A$1000,">="&$C$3,'CPI Log'!$A$4:$A$1000,"<="&$E$3,'CPI Log'!$W$4:$W$1000,"Neither taken") | C55: =IFERROR(B55/B$56,"–")
A56: n (releases) | B56: =SUM(B52:B55)
A59: 5 · Where did the candles close? (relative to the main move)
A60: Strong end = the third on the main-move side (Top when Main Move is Up, Bottom when it is Down). Wick end = the opposite third.
A61: Candle | B61: Strong end | C61: Middle | D61: Wick end | E61: n
A62: 1m candle (8:30) | B62: =IFERROR((COUNTIFS('CPI Log'!$A$4:$A$1000,">="&$C$3,'CPI Log'!$A$4:$A$1000,"<="&$E$3,'CPI Log'!$E$4:$E$1000,"Up",'CPI Log'!$N$4:$N$1000,"Top")+COUNTIFS('CPI Log'!$A$4:$A$1000,">="&$C$3,'CPI Log'!$A$4:$A$1000,"<="&$E$3,'CPI Log'!$E$4:$E$1000,"Down",'CPI Log'!$N$4:$N$1000,"Bottom"))/(E62),"–") | C62: =IFERROR((COUNTIFS('CPI Log'!$A$4:$A$1000,">="&$C$3,'CPI Log'!$A$4:$A$1000,"<="&$E$3,'CPI Log'!$E$4:$E$1000,"Up",'CPI Log'!$N$4:$N$1000,"Middle")+COUNTIFS('CPI Log'!$A$4:$A$1000,">="&$C$3,'CPI Log'!$A$4:$A$1000,"<="&$E$3,'CPI Log'!$E$4:$E$1000,"Down",'CPI Log'!$N$4:$N$1000,"Middle"))/(E62),"–") | D62: =IFERROR((COUNTIFS('CPI Log'!$A$4:$A$1000,">="&$C$3,'CPI Log'!$A$4:$A$1000,"<="&$E$3,'CPI Log'!$E$4:$E$1000,"Up",'CPI Log'!$N$4:$N$1000,"Bottom")+COUNTIFS('CPI Log'!$A$4:$A$1000,">="&$C$3,'CPI Log'!$A$4:$A$1000,"<="&$E$3,'CPI Log'!$E$4:$E$1000,"Down",'CPI Log'!$N$4:$N$1000,"Top"))/(E62),"–") | E62: =COUNTIFS('CPI Log'!$A$4:$A$1000,">="&$C$3,'CPI Log'!$A$4:$A$1000,"<="&$E$3,'CPI Log'!$E$4:$E$1000,"Up",'CPI Log'!$N$4:$N$1000,"Top")+COUNTIFS('CPI Log'!$A$4:$A$1000,">="&$C$3,'CPI Log'!$A$4:$A$1000,"<="&$E$3,'CPI Log'!$E$4:$E$1000,"Down",'CPI Log'!$N$4:$N$1000,"Bottom")+COUNTIFS('CPI Log'!$A$4:$A$1000,">="&$C$3,'CPI Log'!$A$4:$A$1000,"<="&$E$3,'CPI Log'!$E$4:$E$1000,"Up",'CPI Log'!$N$4:$N$1000,"Middle")+COUNTIFS('CPI Log'!$A$4:$A$1000,">="&$C$3,'CPI Log'!$A$4:$A$1000,"<="&$E$3,'CPI Log'!$E$4:$E$1000,"Down",'CPI Log'!$N$4:$N$1000,"Middle")+COUNTIFS('CPI Log'!$A$4:$A$1000,">="&$C$3,'CPI Log'!$A$4:$A$1000,"<="&$E$3,'CPI Log'!$E$4:$E$1000,"Up",'CPI Log'!$N$4:$N$1000,"Bottom")+COUNTIFS('CPI Log'!$A$4:$A$1000,">="&$C$3,'CPI Log'!$A$4:$A$1000,"<="&$E$3,'CPI Log'!$E$4:$E$1000,"Down",'CPI Log'!$N$4:$N$1000,"Top")
A63: 5m candle (8:30-8:34) | B63: =IFERROR((COUNTIFS('CPI Log'!$A$4:$A$1000,">="&$C$3,'CPI Log'!$A$4:$A$1000,"<="&$E$3,'CPI Log'!$E$4:$E$1000,"Up",'CPI Log'!$O$4:$O$1000,"Top")+COUNTIFS('CPI Log'!$A$4:$A$1000,">="&$C$3,'CPI Log'!$A$4:$A$1000,"<="&$E$3,'CPI Log'!$E$4:$E$1000,"Down",'CPI Log'!$O$4:$O$1000,"Bottom"))/(E63),"–") | C63: =IFERROR((COUNTIFS('CPI Log'!$A$4:$A$1000,">="&$C$3,'CPI Log'!$A$4:$A$1000,"<="&$E$3,'CPI Log'!$E$4:$E$1000,"Up",'CPI Log'!$O$4:$O$1000,"Middle")+COUNTIFS('CPI Log'!$A$4:$A$1000,">="&$C$3,'CPI Log'!$A$4:$A$1000,"<="&$E$3,'CPI Log'!$E$4:$E$1000,"Down",'CPI Log'!$O$4:$O$1000,"Middle"))/(E63),"–") | D63: =IFERROR((COUNTIFS('CPI Log'!$A$4:$A$1000,">="&$C$3,'CPI Log'!$A$4:$A$1000,"<="&$E$3,'CPI Log'!$E$4:$E$1000,"Up",'CPI Log'!$O$4:$O$1000,"Bottom")+COUNTIFS('CPI Log'!$A$4:$A$1000,">="&$C$3,'CPI Log'!$A$4:$A$1000,"<="&$E$3,'CPI Log'!$E$4:$E$1000,"Down",'CPI Log'!$O$4:$O$1000,"Top"))/(E63),"–") | E63: =COUNTIFS('CPI Log'!$A$4:$A$1000,">="&$C$3,'CPI Log'!$A$4:$A$1000,"<="&$E$3,'CPI Log'!$E$4:$E$1000,"Up",'CPI Log'!$O$4:$O$1000,"Top")+COUNTIFS('CPI Log'!$A$4:$A$1000,">="&$C$3,'CPI Log'!$A$4:$A$1000,"<="&$E$3,'CPI Log'!$E$4:$E$1000,"Down",'CPI Log'!$O$4:$O$1000,"Bottom")+COUNTIFS('CPI Log'!$A$4:$A$1000,">="&$C$3,'CPI Log'!$A$4:$A$1000,"<="&$E$3,'CPI Log'!$E$4:$E$1000,"Up",'CPI Log'!$O$4:$O$1000,"Middle")+COUNTIFS('CPI Log'!$A$4:$A$1000,">="&$C$3,'CPI Log'!$A$4:$A$1000,"<="&$E$3,'CPI Log'!$E$4:$E$1000,"Down",'CPI Log'!$O$4:$O$1000,"Middle")+COUNTIFS('CPI Log'!$A$4:$A$1000,">="&$C$3,'CPI Log'!$A$4:$A$1000,"<="&$E$3,'CPI Log'!$E$4:$E$1000,"Up",'CPI Log'!$O$4:$O$1000,"Bottom")+COUNTIFS('CPI Log'!$A$4:$A$1000,">="&$C$3,'CPI Log'!$A$4:$A$1000,"<="&$E$3,'CPI Log'!$E$4:$E$1000,"Down",'CPI Log'!$O$4:$O$1000,"Top")
A64: 15m candle (8:30-8:44) | B64: =IFERROR((COUNTIFS('CPI Log'!$A$4:$A$1000,">="&$C$3,'CPI Log'!$A$4:$A$1000,"<="&$E$3,'CPI Log'!$E$4:$E$1000,"Up",'CPI Log'!$P$4:$P$1000,"Top")+COUNTIFS('CPI Log'!$A$4:$A$1000,">="&$C$3,'CPI Log'!$A$4:$A$1000,"<="&$E$3,'CPI Log'!$E$4:$E$1000,"Down",'CPI Log'!$P$4:$P$1000,"Bottom"))/(E64),"–") | C64: =IFERROR((COUNTIFS('CPI Log'!$A$4:$A$1000,">="&$C$3,'CPI Log'!$A$4:$A$1000,"<="&$E$3,'CPI Log'!$E$4:$E$1000,"Up",'CPI Log'!$P$4:$P$1000,"Middle")+COUNTIFS('CPI Log'!$A$4:$A$1000,">="&$C$3,'CPI Log'!$A$4:$A$1000,"<="&$E$3,'CPI Log'!$E$4:$E$1000,"Down",'CPI Log'!$P$4:$P$1000,"Middle"))/(E64),"–") | D64: =IFERROR((COUNTIFS('CPI Log'!$A$4:$A$1000,">="&$C$3,'CPI Log'!$A$4:$A$1000,"<="&$E$3,'CPI Log'!$E$4:$E$1000,"Up",'CPI Log'!$P$4:$P$1000,"Bottom")+COUNTIFS('CPI Log'!$A$4:$A$1000,">="&$C$3,'CPI Log'!$A$4:$A$1000,"<="&$E$3,'CPI Log'!$E$4:$E$1000,"Down",'CPI Log'!$P$4:$P$1000,"Top"))/(E64),"–") | E64: =COUNTIFS('CPI Log'!$A$4:$A$1000,">="&$C$3,'CPI Log'!$A$4:$A$1000,"<="&$E$3,'CPI Log'!$E$4:$E$1000,"Up",'CPI Log'!$P$4:$P$1000,"Top")+COUNTIFS('CPI Log'!$A$4:$A$1000,">="&$C$3,'CPI Log'!$A$4:$A$1000,"<="&$E$3,'CPI Log'!$E$4:$E$1000,"Down",'CPI Log'!$P$4:$P$1000,"Bottom")+COUNTIFS('CPI Log'!$A$4:$A$1000,">="&$C$3,'CPI Log'!$A$4:$A$1000,"<="&$E$3,'CPI Log'!$E$4:$E$1000,"Up",'CPI Log'!$P$4:$P$1000,"Middle")+COUNTIFS('CPI Log'!$A$4:$A$1000,">="&$C$3,'CPI Log'!$A$4:$A$1000,"<="&$E$3,'CPI Log'!$E$4:$E$1000,"Down",'CPI Log'!$P$4:$P$1000,"Middle")+COUNTIFS('CPI Log'!$A$4:$A$1000,">="&$C$3,'CPI Log'!$A$4:$A$1000,"<="&$E$3,'CPI Log'!$E$4:$E$1000,"Up",'CPI Log'!$P$4:$P$1000,"Bottom")+COUNTIFS('CPI Log'!$A$4:$A$1000,">="&$C$3,'CPI Log'!$A$4:$A$1000,"<="&$E$3,'CPI Log'!$E$4:$E$1000,"Down",'CPI Log'!$P$4:$P$1000,"Top")
A67: 6 · How deep was the pullback before the main move continued?
A68: Use this for entries and stops: e.g. if most Continued cases reach 62% (OTE), a limit order at 62% gets filled most of the time.
A69: Deepest pullback % | B69: All | C69: When it Continued
A70: Average pullback | B70: =IFERROR(AVERAGEIFS('CPI Log'!$S$4:$S$1000,'CPI Log'!$A$4:$A$1000,">="&$C$3,'CPI Log'!$A$4:$A$1000,"<="&$E$3,'CPI Log'!$S$4:$S$1000,">=0"),"–") | C70: =IFERROR(AVERAGEIFS('CPI Log'!$S$4:$S$1000,'CPI Log'!$A$4:$A$1000,">="&$C$3,'CPI Log'!$A$4:$A$1000,"<="&$E$3,'CPI Log'!$V$4:$V$1000,"Continued",'CPI Log'!$S$4:$S$1000,">=0"),"–")
A71: Reached 50% (half-way / equilibrium) | B71: =IFERROR((COUNTIFS('CPI Log'!$A$4:$A$1000,">="&$C$3,'CPI Log'!$A$4:$A$1000,"<="&$E$3,'CPI Log'!$S$4:$S$1000,">=50"))/(B$76),"–") | C71: =IFERROR((COUNTIFS('CPI Log'!$A$4:$A$1000,">="&$C$3,'CPI Log'!$A$4:$A$1000,"<="&$E$3,'CPI Log'!$S$4:$S$1000,">=50",'CPI Log'!$V$4:$V$1000,"Continued"))/(C$76),"–")
A72: Reached 62% (OTE starts) | B72: =IFERROR((COUNTIFS('CPI Log'!$A$4:$A$1000,">="&$C$3,'CPI Log'!$A$4:$A$1000,"<="&$E$3,'CPI Log'!$S$4:$S$1000,">=62"))/(B$76),"–") | C72: =IFERROR((COUNTIFS('CPI Log'!$A$4:$A$1000,">="&$C$3,'CPI Log'!$A$4:$A$1000,"<="&$E$3,'CPI Log'!$S$4:$S$1000,">=62",'CPI Log'!$V$4:$V$1000,"Continued"))/(C$76),"–")
A73: Reached 70.5% (OTE sweet spot) | B73: =IFERROR((COUNTIFS('CPI Log'!$A$4:$A$1000,">="&$C$3,'CPI Log'!$A$4:$A$1000,"<="&$E$3,'CPI Log'!$S$4:$S$1000,">=70.5"))/(B$76),"–") | C73: =IFERROR((COUNTIFS('CPI Log'!$A$4:$A$1000,">="&$C$3,'CPI Log'!$A$4:$A$1000,"<="&$E$3,'CPI Log'!$S$4:$S$1000,">=70.5",'CPI Log'!$V$4:$V$1000,"Continued"))/(C$76),"–")
A74: Reached 79% (OTE ends) | B74: =IFERROR((COUNTIFS('CPI Log'!$A$4:$A$1000,">="&$C$3,'CPI Log'!$A$4:$A$1000,"<="&$E$3,'CPI Log'!$S$4:$S$1000,">=79"))/(B$76),"–") | C74: =IFERROR((COUNTIFS('CPI Log'!$A$4:$A$1000,">="&$C$3,'CPI Log'!$A$4:$A$1000,"<="&$E$3,'CPI Log'!$S$4:$S$1000,">=79",'CPI Log'!$V$4:$V$1000,"Continued"))/(C$76),"–")
A75: Reached 100% (back to the 8:30 open) | B75: =IFERROR((COUNTIFS('CPI Log'!$A$4:$A$1000,">="&$C$3,'CPI Log'!$A$4:$A$1000,"<="&$E$3,'CPI Log'!$S$4:$S$1000,">=100"))/(B$76),"–")
A76: n (releases) | B76: =COUNTIFS('CPI Log'!$A$4:$A$1000,">="&$C$3,'CPI Log'!$A$4:$A$1000,"<="&$E$3,'CPI Log'!$S$4:$S$1000,">=0") | C76: =COUNTIFS('CPI Log'!$A$4:$A$1000,">="&$C$3,'CPI Log'!$A$4:$A$1000,"<="&$E$3,'CPI Log'!$S$4:$S$1000,">=0",'CPI Log'!$V$4:$V$1000,"Continued")
A79: 7 · Did NQ move the 'logical' way for the CPI number?
A80: With data = Hotter → Main Move Down, or Cooler → Main Move Up. In line / Mixed are left out.
A81: Main move vs CPI | B81: # | C81: %
A82: With data | B82: =COUNTIFS('CPI Log'!$A$4:$A$1000,">="&$C$3,'CPI Log'!$A$4:$A$1000,"<="&$E$3,'CPI Log'!$M$4:$M$1000,$A82) | C82: =IFERROR(B82/B$84,"–")
A83: Against data | B83: =COUNTIFS('CPI Log'!$A$4:$A$1000,">="&$C$3,'CPI Log'!$A$4:$A$1000,"<="&$E$3,'CPI Log'!$M$4:$M$1000,$A83) | C83: =IFERROR(B83/B$84,"–")
A84: n (Hotter or Cooler) | B84: =SUM(B82:B83)
A86: CPI vs forecast | B86: Releases | C86: Main move Up | D86: Main move Down
A87: Hotter | B87: =COUNTIFS('CPI Log'!$A$4:$A$1000,">="&$C$3,'CPI Log'!$A$4:$A$1000,"<="&$E$3,'CPI Log'!$L$4:$L$1000,$A87,'CPI Log'!$E$4:$E$1000,"Up")+COUNTIFS('CPI Log'!$A$4:$A$1000,">="&$C$3,'CPI Log'!$A$4:$A$1000,"<="&$E$3,'CPI Log'!$L$4:$L$1000,$A87,'CPI Log'!$E$4:$E$1000,"Down") | C87: =IFERROR((COUNTIFS('CPI Log'!$A$4:$A$1000,">="&$C$3,'CPI Log'!$A$4:$A$1000,"<="&$E$3,'CPI Log'!$L$4:$L$1000,$A87,'CPI Log'!$E$4:$E$1000,"Up"))/(B87),"–") | D87: =IFERROR((COUNTIFS('CPI Log'!$A$4:$A$1000,">="&$C$3,'CPI Log'!$A$4:$A$1000,"<="&$E$3,'CPI Log'!$L$4:$L$1000,$A87,'CPI Log'!$E$4:$E$1000,"Down"))/(B87),"–")
A88: Cooler | B88: =COUNTIFS('CPI Log'!$A$4:$A$1000,">="&$C$3,'CPI Log'!$A$4:$A$1000,"<="&$E$3,'CPI Log'!$L$4:$L$1000,$A88,'CPI Log'!$E$4:$E$1000,"Up")+COUNTIFS('CPI Log'!$A$4:$A$1000,">="&$C$3,'CPI Log'!$A$4:$A$1000,"<="&$E$3,'CPI Log'!$L$4:$L$1000,$A88,'CPI Log'!$E$4:$E$1000,"Down") | C88: =IFERROR((COUNTIFS('CPI Log'!$A$4:$A$1000,">="&$C$3,'CPI Log'!$A$4:$A$1000,"<="&$E$3,'CPI Log'!$L$4:$L$1000,$A88,'CPI Log'!$E$4:$E$1000,"Up"))/(B88),"–") | D88: =IFERROR((COUNTIFS('CPI Log'!$A$4:$A$1000,">="&$C$3,'CPI Log'!$A$4:$A$1000,"<="&$E$3,'CPI Log'!$L$4:$L$1000,$A88,'CPI Log'!$E$4:$E$1000,"Down"))/(B88),"–")
A89: In line | B89: =COUNTIFS('CPI Log'!$A$4:$A$1000,">="&$C$3,'CPI Log'!$A$4:$A$1000,"<="&$E$3,'CPI Log'!$L$4:$L$1000,$A89,'CPI Log'!$E$4:$E$1000,"Up")+COUNTIFS('CPI Log'!$A$4:$A$1000,">="&$C$3,'CPI Log'!$A$4:$A$1000,"<="&$E$3,'CPI Log'!$L$4:$L$1000,$A89,'CPI Log'!$E$4:$E$1000,"Down") | C89: =IFERROR((COUNTIFS('CPI Log'!$A$4:$A$1000,">="&$C$3,'CPI Log'!$A$4:$A$1000,"<="&$E$3,'CPI Log'!$L$4:$L$1000,$A89,'CPI Log'!$E$4:$E$1000,"Up"))/(B89),"–") | D89: =IFERROR((COUNTIFS('CPI Log'!$A$4:$A$1000,">="&$C$3,'CPI Log'!$A$4:$A$1000,"<="&$E$3,'CPI Log'!$L$4:$L$1000,$A89,'CPI Log'!$E$4:$E$1000,"Down"))/(B89),"–")
A90: Mixed | B90: =COUNTIFS('CPI Log'!$A$4:$A$1000,">="&$C$3,'CPI Log'!$A$4:$A$1000,"<="&$E$3,'CPI Log'!$L$4:$L$1000,$A90,'CPI Log'!$E$4:$E$1000,"Up")+COUNTIFS('CPI Log'!$A$4:$A$1000,">="&$C$3,'CPI Log'!$A$4:$A$1000,"<="&$E$3,'CPI Log'!$L$4:$L$1000,$A90,'CPI Log'!$E$4:$E$1000,"Down") | C90: =IFERROR((COUNTIFS('CPI Log'!$A$4:$A$1000,">="&$C$3,'CPI Log'!$A$4:$A$1000,"<="&$E$3,'CPI Log'!$L$4:$L$1000,$A90,'CPI Log'!$E$4:$E$1000,"Up"))/(B90),"–") | D90: =IFERROR((COUNTIFS('CPI Log'!$A$4:$A$1000,">="&$C$3,'CPI Log'!$A$4:$A$1000,"<="&$E$3,'CPI Log'!$L$4:$L$1000,$A90,'CPI Log'!$E$4:$E$1000,"Down"))/(B90),"–")
A93: 8 · Average size in points (your original columns)
A94: Only real numbers are averaged - cells with text like 'Same' are skipped.
A95: Average (points) | B95: All | C95: Main move Up | D95: Main move Down
A96: Wick pts (when there was a wick) | B96: =IFERROR(AVERAGEIFS('CPI Log'!$D$4:$D$1000,'CPI Log'!$A$4:$A$1000,">="&$C$3,'CPI Log'!$A$4:$A$1000,"<="&$E$3,'CPI Log'!$D$4:$D$1000,">-1000000"),"–") | C96: =IFERROR(AVERAGEIFS('CPI Log'!$D$4:$D$1000,'CPI Log'!$A$4:$A$1000,">="&$C$3,'CPI Log'!$A$4:$A$1000,"<="&$E$3,'CPI Log'!$D$4:$D$1000,">-1000000",'CPI Log'!$E$4:$E$1000,"Up"),"–") | D96: =IFERROR(AVERAGEIFS('CPI Log'!$D$4:$D$1000,'CPI Log'!$A$4:$A$1000,">="&$C$3,'CPI Log'!$A$4:$A$1000,"<="&$E$3,'CPI Log'!$D$4:$D$1000,">-1000000",'CPI Log'!$E$4:$E$1000,"Down"),"–")
A97: 15sec move | B97: =IFERROR(AVERAGEIFS('CPI Log'!$F$4:$F$1000,'CPI Log'!$A$4:$A$1000,">="&$C$3,'CPI Log'!$A$4:$A$1000,"<="&$E$3,'CPI Log'!$F$4:$F$1000,">-1000000"),"–") | C97: =IFERROR(AVERAGEIFS('CPI Log'!$F$4:$F$1000,'CPI Log'!$A$4:$A$1000,">="&$C$3,'CPI Log'!$A$4:$A$1000,"<="&$E$3,'CPI Log'!$F$4:$F$1000,">-1000000",'CPI Log'!$E$4:$E$1000,"Up"),"–") | D97: =IFERROR(AVERAGEIFS('CPI Log'!$F$4:$F$1000,'CPI Log'!$A$4:$A$1000,">="&$C$3,'CPI Log'!$A$4:$A$1000,"<="&$E$3,'CPI Log'!$F$4:$F$1000,">-1000000",'CPI Log'!$E$4:$E$1000,"Down"),"–")
A98: 30sec move | B98: =IFERROR(AVERAGEIFS('CPI Log'!$G$4:$G$1000,'CPI Log'!$A$4:$A$1000,">="&$C$3,'CPI Log'!$A$4:$A$1000,"<="&$E$3,'CPI Log'!$G$4:$G$1000,">-1000000"),"–") | C98: =IFERROR(AVERAGEIFS('CPI Log'!$G$4:$G$1000,'CPI Log'!$A$4:$A$1000,">="&$C$3,'CPI Log'!$A$4:$A$1000,"<="&$E$3,'CPI Log'!$G$4:$G$1000,">-1000000",'CPI Log'!$E$4:$E$1000,"Up"),"–") | D98: =IFERROR(AVERAGEIFS('CPI Log'!$G$4:$G$1000,'CPI Log'!$A$4:$A$1000,">="&$C$3,'CPI Log'!$A$4:$A$1000,"<="&$E$3,'CPI Log'!$G$4:$G$1000,">-1000000",'CPI Log'!$E$4:$E$1000,"Down"),"–")
A99: 1min move | B99: =IFERROR(AVERAGEIFS('CPI Log'!$H$4:$H$1000,'CPI Log'!$A$4:$A$1000,">="&$C$3,'CPI Log'!$A$4:$A$1000,"<="&$E$3,'CPI Log'!$H$4:$H$1000,">-1000000"),"–") | C99: =IFERROR(AVERAGEIFS('CPI Log'!$H$4:$H$1000,'CPI Log'!$A$4:$A$1000,">="&$C$3,'CPI Log'!$A$4:$A$1000,"<="&$E$3,'CPI Log'!$H$4:$H$1000,">-1000000",'CPI Log'!$E$4:$E$1000,"Up"),"–") | D99: =IFERROR(AVERAGEIFS('CPI Log'!$H$4:$H$1000,'CPI Log'!$A$4:$A$1000,">="&$C$3,'CPI Log'!$A$4:$A$1000,"<="&$E$3,'CPI Log'!$H$4:$H$1000,">-1000000",'CPI Log'!$E$4:$E$1000,"Down"),"–")
A100: Scam Wick (15 sec before) | B100: =IFERROR(AVERAGEIFS('CPI Log'!$J$4:$J$1000,'CPI Log'!$A$4:$A$1000,">="&$C$3,'CPI Log'!$A$4:$A$1000,"<="&$E$3,'CPI Log'!$J$4:$J$1000,">-1000000"),"–") | C100: =IFERROR(AVERAGEIFS('CPI Log'!$J$4:$J$1000,'CPI Log'!$A$4:$A$1000,">="&$C$3,'CPI Log'!$A$4:$A$1000,"<="&$E$3,'CPI Log'!$J$4:$J$1000,">-1000000",'CPI Log'!$E$4:$E$1000,"Up"),"–") | D100: =IFERROR(AVERAGEIFS('CPI Log'!$J$4:$J$1000,'CPI Log'!$A$4:$A$1000,">="&$C$3,'CPI Log'!$A$4:$A$1000,"<="&$E$3,'CPI Log'!$J$4:$J$1000,">-1000000",'CPI Log'!$E$4:$E$1000,"Down"),"–")
A103: 9 · Straddle results
A104: Chart backtests don't show news slippage/spread - real fills on stop orders are usually worse.
A105: Result | B105: # | C105: %
A106: TP | B106: =COUNTIFS('CPI Log'!$A$4:$A$1000,">="&$C$3,'CPI Log'!$A$4:$A$1000,"<="&$E$3,'CPI Log'!$I$4:$I$1000,$A106) | C106: =IFERROR(B106/B$109,"–")
A107: SL | B107: =COUNTIFS('CPI Log'!$A$4:$A$1000,">="&$C$3,'CPI Log'!$A$4:$A$1000,"<="&$E$3,'CPI Log'!$I$4:$I$1000,$A107) | C107: =IFERROR(B107/B$109,"–")
A108: BE | B108: =COUNTIFS('CPI Log'!$A$4:$A$1000,">="&$C$3,'CPI Log'!$A$4:$A$1000,"<="&$E$3,'CPI Log'!$I$4:$I$1000,$A108) | C108: =IFERROR(B108/B$109,"–")
A109: n (N/A not counted) | B109: =SUM(B106:B108)
A112: 10 · ICT: liquidity taken by the MAIN MOVE (by 8:45) → what happened after the 1st minute?
A113: Biggest level taken | B113: n | C113: Continued | D113: Back to open | E113: Partial retrace | F113: Stalled / chop
A114: None | B114: =COUNTIFS('CPI Log'!$A$4:$A$1000,">="&$C$3,'CPI Log'!$A$4:$A$1000,"<="&$E$3,'CPI Log'!$AA$4:$AA$1000,$A114,'CPI Log'!$V$4:$V$1000,"Continued")+COUNTIFS('CPI Log'!$A$4:$A$1000,">="&$C$3,'CPI Log'!$A$4:$A$1000,"<="&$E$3,'CPI Log'!$AA$4:$AA$1000,$A114,'CPI Log'!$V$4:$V$1000,"Back to open")+COUNTIFS('CPI Log'!$A$4:$A$1000,">="&$C$3,'CPI Log'!$A$4:$A$1000,"<="&$E$3,'CPI Log'!$AA$4:$AA$1000,$A114,'CPI Log'!$V$4:$V$1000,"Partial retrace")+COUNTIFS('CPI Log'!$A$4:$A$1000,">="&$C$3,'CPI Log'!$A$4:$A$1000,"<="&$E$3,'CPI Log'!$AA$4:$AA$1000,$A114,'CPI Log'!$V$4:$V$1000,"Stalled / chop") | C114: =IFERROR((COUNTIFS('CPI Log'!$A$4:$A$1000,">="&$C$3,'CPI Log'!$A$4:$A$1000,"<="&$E$3,'CPI Log'!$AA$4:$AA$1000,$A114,'CPI Log'!$V$4:$V$1000,"Continued"))/($B114),"–") | D114: =IFERROR((COUNTIFS('CPI Log'!$A$4:$A$1000,">="&$C$3,'CPI Log'!$A$4:$A$1000,"<="&$E$3,'CPI Log'!$AA$4:$AA$1000,$A114,'CPI Log'!$V$4:$V$1000,"Back to open"))/($B114),"–") | E114: =IFERROR((COUNTIFS('CPI Log'!$A$4:$A$1000,">="&$C$3,'CPI Log'!$A$4:$A$1000,"<="&$E$3,'CPI Log'!$AA$4:$AA$1000,$A114,'CPI Log'!$V$4:$V$1000,"Partial retrace"))/($B114),"–") | F114: =IFERROR((COUNTIFS('CPI Log'!$A$4:$A$1000,">="&$C$3,'CPI Log'!$A$4:$A$1000,"<="&$E$3,'CPI Log'!$AA$4:$AA$1000,$A114,'CPI Log'!$V$4:$V$1000,"Stalled / chop"))/($B114),"–")
A115: Pre-news high/low | B115: =COUNTIFS('CPI Log'!$A$4:$A$1000,">="&$C$3,'CPI Log'!$A$4:$A$1000,"<="&$E$3,'CPI Log'!$AA$4:$AA$1000,$A115,'CPI Log'!$V$4:$V$1000,"Continued")+COUNTIFS('CPI Log'!$A$4:$A$1000,">="&$C$3,'CPI Log'!$A$4:$A$1000,"<="&$E$3,'CPI Log'!$AA$4:$AA$1000,$A115,'CPI Log'!$V$4:$V$1000,"Back to open")+COUNTIFS('CPI Log'!$A$4:$A$1000,">="&$C$3,'CPI Log'!$A$4:$A$1000,"<="&$E$3,'CPI Log'!$AA$4:$AA$1000,$A115,'CPI Log'!$V$4:$V$1000,"Partial retrace")+COUNTIFS('CPI Log'!$A$4:$A$1000,">="&$C$3,'CPI Log'!$A$4:$A$1000,"<="&$E$3,'CPI Log'!$AA$4:$AA$1000,$A115,'CPI Log'!$V$4:$V$1000,"Stalled / chop") | C115: =IFERROR((COUNTIFS('CPI Log'!$A$4:$A$1000,">="&$C$3,'CPI Log'!$A$4:$A$1000,"<="&$E$3,'CPI Log'!$AA$4:$AA$1000,$A115,'CPI Log'!$V$4:$V$1000,"Continued"))/($B115),"–") | D115: =IFERROR((COUNTIFS('CPI Log'!$A$4:$A$1000,">="&$C$3,'CPI Log'!$A$4:$A$1000,"<="&$E$3,'CPI Log'!$AA$4:$AA$1000,$A115,'CPI Log'!$V$4:$V$1000,"Back to open"))/($B115),"–") | E115: =IFERROR((COUNTIFS('CPI Log'!$A$4:$A$1000,">="&$C$3,'CPI Log'!$A$4:$A$1000,"<="&$E$3,'CPI Log'!$AA$4:$AA$1000,$A115,'CPI Log'!$V$4:$V$1000,"Partial retrace"))/($B115),"–") | F115: =IFERROR((COUNTIFS('CPI Log'!$A$4:$A$1000,">="&$C$3,'CPI Log'!$A$4:$A$1000,"<="&$E$3,'CPI Log'!$AA$4:$AA$1000,$A115,'CPI Log'!$V$4:$V$1000,"Stalled / chop"))/($B115),"–")
A116: Asia high/low | B116: =COUNTIFS('CPI Log'!$A$4:$A$1000,">="&$C$3,'CPI Log'!$A$4:$A$1000,"<="&$E$3,'CPI Log'!$AA$4:$AA$1000,$A116,'CPI Log'!$V$4:$V$1000,"Continued")+COUNTIFS('CPI Log'!$A$4:$A$1000,">="&$C$3,'CPI Log'!$A$4:$A$1000,"<="&$E$3,'CPI Log'!$AA$4:$AA$1000,$A116,'CPI Log'!$V$4:$V$1000,"Back to open")+COUNTIFS('CPI Log'!$A$4:$A$1000,">="&$C$3,'CPI Log'!$A$4:$A$1000,"<="&$E$3,'CPI Log'!$AA$4:$AA$1000,$A116,'CPI Log'!$V$4:$V$1000,"Partial retrace")+COUNTIFS('CPI Log'!$A$4:$A$1000,">="&$C$3,'CPI Log'!$A$4:$A$1000,"<="&$E$3,'CPI Log'!$AA$4:$AA$1000,$A116,'CPI Log'!$V$4:$V$1000,"Stalled / chop") | C116: =IFERROR((COUNTIFS('CPI Log'!$A$4:$A$1000,">="&$C$3,'CPI Log'!$A$4:$A$1000,"<="&$E$3,'CPI Log'!$AA$4:$AA$1000,$A116,'CPI Log'!$V$4:$V$1000,"Continued"))/($B116),"–") | D116: =IFERROR((COUNTIFS('CPI Log'!$A$4:$A$1000,">="&$C$3,'CPI Log'!$A$4:$A$1000,"<="&$E$3,'CPI Log'!$AA$4:$AA$1000,$A116,'CPI Log'!$V$4:$V$1000,"Back to open"))/($B116),"–") | E116: =IFERROR((COUNTIFS('CPI Log'!$A$4:$A$1000,">="&$C$3,'CPI Log'!$A$4:$A$1000,"<="&$E$3,'CPI Log'!$AA$4:$AA$1000,$A116,'CPI Log'!$V$4:$V$1000,"Partial retrace"))/($B116),"–") | F116: =IFERROR((COUNTIFS('CPI Log'!$A$4:$A$1000,">="&$C$3,'CPI Log'!$A$4:$A$1000,"<="&$E$3,'CPI Log'!$AA$4:$AA$1000,$A116,'CPI Log'!$V$4:$V$1000,"Stalled / chop"))/($B116),"–")
A117: London high/low | B117: =COUNTIFS('CPI Log'!$A$4:$A$1000,">="&$C$3,'CPI Log'!$A$4:$A$1000,"<="&$E$3,'CPI Log'!$AA$4:$AA$1000,$A117,'CPI Log'!$V$4:$V$1000,"Continued")+COUNTIFS('CPI Log'!$A$4:$A$1000,">="&$C$3,'CPI Log'!$A$4:$A$1000,"<="&$E$3,'CPI Log'!$AA$4:$AA$1000,$A117,'CPI Log'!$V$4:$V$1000,"Back to open")+COUNTIFS('CPI Log'!$A$4:$A$1000,">="&$C$3,'CPI Log'!$A$4:$A$1000,"<="&$E$3,'CPI Log'!$AA$4:$AA$1000,$A117,'CPI Log'!$V$4:$V$1000,"Partial retrace")+COUNTIFS('CPI Log'!$A$4:$A$1000,">="&$C$3,'CPI Log'!$A$4:$A$1000,"<="&$E$3,'CPI Log'!$AA$4:$AA$1000,$A117,'CPI Log'!$V$4:$V$1000,"Stalled / chop") | C117: =IFERROR((COUNTIFS('CPI Log'!$A$4:$A$1000,">="&$C$3,'CPI Log'!$A$4:$A$1000,"<="&$E$3,'CPI Log'!$AA$4:$AA$1000,$A117,'CPI Log'!$V$4:$V$1000,"Continued"))/($B117),"–") | D117: =IFERROR((COUNTIFS('CPI Log'!$A$4:$A$1000,">="&$C$3,'CPI Log'!$A$4:$A$1000,"<="&$E$3,'CPI Log'!$AA$4:$AA$1000,$A117,'CPI Log'!$V$4:$V$1000,"Back to open"))/($B117),"–") | E117: =IFERROR((COUNTIFS('CPI Log'!$A$4:$A$1000,">="&$C$3,'CPI Log'!$A$4:$A$1000,"<="&$E$3,'CPI Log'!$AA$4:$AA$1000,$A117,'CPI Log'!$V$4:$V$1000,"Partial retrace"))/($B117),"–") | F117: =IFERROR((COUNTIFS('CPI Log'!$A$4:$A$1000,">="&$C$3,'CPI Log'!$A$4:$A$1000,"<="&$E$3,'CPI Log'!$AA$4:$AA$1000,$A117,'CPI Log'!$V$4:$V$1000,"Stalled / chop"))/($B117),"–")
A118: Prev day high/low | B118: =COUNTIFS('CPI Log'!$A$4:$A$1000,">="&$C$3,'CPI Log'!$A$4:$A$1000,"<="&$E$3,'CPI Log'!$AA$4:$AA$1000,$A118,'CPI Log'!$V$4:$V$1000,"Continued")+COUNTIFS('CPI Log'!$A$4:$A$1000,">="&$C$3,'CPI Log'!$A$4:$A$1000,"<="&$E$3,'CPI Log'!$AA$4:$AA$1000,$A118,'CPI Log'!$V$4:$V$1000,"Back to open")+COUNTIFS('CPI Log'!$A$4:$A$1000,">="&$C$3,'CPI Log'!$A$4:$A$1000,"<="&$E$3,'CPI Log'!$AA$4:$AA$1000,$A118,'CPI Log'!$V$4:$V$1000,"Partial retrace")+COUNTIFS('CPI Log'!$A$4:$A$1000,">="&$C$3,'CPI Log'!$A$4:$A$1000,"<="&$E$3,'CPI Log'!$AA$4:$AA$1000,$A118,'CPI Log'!$V$4:$V$1000,"Stalled / chop") | C118: =IFERROR((COUNTIFS('CPI Log'!$A$4:$A$1000,">="&$C$3,'CPI Log'!$A$4:$A$1000,"<="&$E$3,'CPI Log'!$AA$4:$AA$1000,$A118,'CPI Log'!$V$4:$V$1000,"Continued"))/($B118),"–") | D118: =IFERROR((COUNTIFS('CPI Log'!$A$4:$A$1000,">="&$C$3,'CPI Log'!$A$4:$A$1000,"<="&$E$3,'CPI Log'!$AA$4:$AA$1000,$A118,'CPI Log'!$V$4:$V$1000,"Back to open"))/($B118),"–") | E118: =IFERROR((COUNTIFS('CPI Log'!$A$4:$A$1000,">="&$C$3,'CPI Log'!$A$4:$A$1000,"<="&$E$3,'CPI Log'!$AA$4:$AA$1000,$A118,'CPI Log'!$V$4:$V$1000,"Partial retrace"))/($B118),"–") | F118: =IFERROR((COUNTIFS('CPI Log'!$A$4:$A$1000,">="&$C$3,'CPI Log'!$A$4:$A$1000,"<="&$E$3,'CPI Log'!$AA$4:$AA$1000,$A118,'CPI Log'!$V$4:$V$1000,"Stalled / chop"))/($B118),"–")
A119: Prev week high/low | B119: =COUNTIFS('CPI Log'!$A$4:$A$1000,">="&$C$3,'CPI Log'!$A$4:$A$1000,"<="&$E$3,'CPI Log'!$AA$4:$AA$1000,$A119,'CPI Log'!$V$4:$V$1000,"Continued")+COUNTIFS('CPI Log'!$A$4:$A$1000,">="&$C$3,'CPI Log'!$A$4:$A$1000,"<="&$E$3,'CPI Log'!$AA$4:$AA$1000,$A119,'CPI Log'!$V$4:$V$1000,"Back to open")+COUNTIFS('CPI Log'!$A$4:$A$1000,">="&$C$3,'CPI Log'!$A$4:$A$1000,"<="&$E$3,'CPI Log'!$AA$4:$AA$1000,$A119,'CPI Log'!$V$4:$V$1000,"Partial retrace")+COUNTIFS('CPI Log'!$A$4:$A$1000,">="&$C$3,'CPI Log'!$A$4:$A$1000,"<="&$E$3,'CPI Log'!$AA$4:$AA$1000,$A119,'CPI Log'!$V$4:$V$1000,"Stalled / chop") | C119: =IFERROR((COUNTIFS('CPI Log'!$A$4:$A$1000,">="&$C$3,'CPI Log'!$A$4:$A$1000,"<="&$E$3,'CPI Log'!$AA$4:$AA$1000,$A119,'CPI Log'!$V$4:$V$1000,"Continued"))/($B119),"–") | D119: =IFERROR((COUNTIFS('CPI Log'!$A$4:$A$1000,">="&$C$3,'CPI Log'!$A$4:$A$1000,"<="&$E$3,'CPI Log'!$AA$4:$AA$1000,$A119,'CPI Log'!$V$4:$V$1000,"Back to open"))/($B119),"–") | E119: =IFERROR((COUNTIFS('CPI Log'!$A$4:$A$1000,">="&$C$3,'CPI Log'!$A$4:$A$1000,"<="&$E$3,'CPI Log'!$AA$4:$AA$1000,$A119,'CPI Log'!$V$4:$V$1000,"Partial retrace"))/($B119),"–") | F119: =IFERROR((COUNTIFS('CPI Log'!$A$4:$A$1000,">="&$C$3,'CPI Log'!$A$4:$A$1000,"<="&$E$3,'CPI Log'!$AA$4:$AA$1000,$A119,'CPI Log'!$V$4:$V$1000,"Stalled / chop"))/($B119),"–")
A122: 11 · ICT: liquidity taken by the WICK → what happened after the 1st minute?
A123: Biggest level taken | B123: n | C123: Continued | D123: Back to open | E123: Partial retrace | F123: Stalled / chop
...

Sheet Guide
A1: HOW TO USE THIS CPI BACKTEST SHEET
A2: Hover any header in the CPI Log tab to see the same definitions there.
A3: QUICK START
A4: 1 | B4: One row = one CPI | C4: Work left → right while you replay the day with TradingView Bar Replay. The columns follow the order things happen.
A5: 2 | B5: New York time | C5: Set the TradingView chart timezone to New York (UTC-4/-5). CPI is always 8:30 NY time and every time window in this sheet uses NY time.
A6: 3 | B6: White vs grey | C6: White cells: you fill them. Grey cells: automatic - don't type in them.
A7: 4 | B7: Dropdowns & numbers | C7: ▼ = pick from the dropdown. Number columns take numbers only (instead of 'Same', type the number again).
A8: 5 | B8: No hindsight | C8: Fill the ICT context (bias, levels to watch) at 8:29, BEFORE you play the release.
A9: 6 | B9: Chart link | C9: For every row save a TradingView snapshot (camera icon → Copy link) in 'Chart link', so later you can see the day in one click.
A10: 7 | B10: Stats | C10: The Stats tab updates by itself. To test only a period (e.g. 2023+), change the two dates at the top of Stats.
A12: WORDS USED IN THIS SHEET
B13: 8:30 open | C13: The open price of the 8:30:00 candle = the price at the moment CPI comes out.
B14: 1-min candle | C14: The 8:30 one-minute candle (8:30:00-8:30:59). Its HIGH is buy-side liquidity (BSL), its LOW is sell-side liquidity (SSL). Your 'initial wick' high/low is inside this candle.
B15: Main side / Wick side | C15: Main side = the end of the 1-min candle in your Main Move direction (the HIGH when Main Move is Up). Wick side = the other end.
B16: Taken | C16: Price trades beyond the level, even by 1 tick. A sweep counts.
B17: Time windows (NY) | C17: 0-15 sec = 8:30:00-8:30:14 · 15-30 sec = 8:30:15-8:30:29 · 30-60 sec = 8:30:30-8:30:59 · 1-5 min = 8:31:00-8:34:59 · 5-15 min = 8:35:00-8:44:59 · 15-60 min = 8:45:00-9:29:59 · 9:30-11:00 · 11:00-16:00 · Not by 16:00 = didn't happen that day.
B18: Deepest pullback % | C18: Put a Fib with 0 on the 1-min main-side extreme and 100 on the 8:30 open (tick 'Reverse' in the Fib settings if it's upside down). Record the deepest level price reached BEFORE it broke the 1-min main-side extreme; stop checking at 8:45. 0 = no pullback · 50 = half-way · 62-79 = OTE · 100 = back at the 8:30 open · 120 = 20% past it. Type 62, not 62%.
B19: Outcome (auto) | C19: Back to open = pullback reached 100 · Continued = main side taken by 8:45 (1-5 or 5-15 min) with pullback under 100 · Partial retrace = not taken by 8:45, pullback 50-99 · Stalled / chop = not taken by 8:45, pullback under 50.
B20: Candle close | C20: Split the candle's full range (wicks included) into 3 equal parts: which part did it close in? 1m = 8:30 candle · 5m = 8:30-8:34 · 15m = 8:30-8:44.
B21: Back to 8:30 open | C21: The first time price trades back at the 8:30 open after the main move started.
B22: At the open, price… | C22: Swept & resumed = after touching the open it turned and made a new high/low in the main direction before taking the 1-min wick side · Broke through = it took the 1-min wick side first · Chopped around = neither by 16:00 · Never came back.
B23: CPI vs forecast | C23: ForexFactory history: CPI m/m and Core CPI m/m, actual vs forecast. Both higher (or one higher, one equal) = Hotter · both lower (or one lower, one equal) = Cooler · both equal = In line · one higher, one lower = Mixed.
B24: Liquidity levels | C24: Pre-news = high/low of 7:00-8:29 · London = 2:00-5:00 · Asia = 20:00-00:00 (evening before) · Prev day = yesterday's daily candle · Prev week = last week's candle. Pick the BIGGEST one taken: Prev week > Prev day > London > Asia > Pre-news. None = nothing taken.
... B29: R | C29: Result in multiples of your risk: +2 = made 2x the risk, -1 = full stop loss, 0 = breakeven.
A31: COLUMN GUIDE (the Example column is made up - it shows one complete row)
A32: Col | B32: Column | C32: What it means | D32: How to fill | E32: Example
A33: A | B33: CPI Release Date | C33: Day the CPI number came out (8:30 New York time). | D33: Type the date, e.g. 12 Aug 2026. | E33: (release date)
A34: B | B34: Day | C34: Weekday of the release. | D34: Nothing - fills itself. (Old rows you paste keep the day you typed.) | E34: Wed (auto)
A35: C | B35: Wick | C35: Direction of the first spike when the number hits (the quick move AGAINST the main move). | D35: ▼ Up / Down, or No Wick if price went straight in the main direction. | E35: Down
A36: D | B36: Wick pts | C36: Size of that first spike in points. | D36: Number. Leave empty if No Wick. | E36: 12
A37: E | B37: Main Move | C37: Direction price really went after the wick. | D37: ▼ Up / Down. Most other columns are read relative to this. | E37: Up
A38: F | B38: 15sec move | C38: How far the main move went in the first 15 seconds (points) - keep your usual method. | D38: Number only. If nothing changed, type the same number again instead of 'Same' (text can't be averaged). | E38: 80
A39: G | B39: 30sec move | C39: Same, for the first 30 seconds. | D39: Number only (no 'Same'). A move the other way is captured by 'Deepest pullback %'. | E39: 95
A40: H | B40: 1min move | C40: Same, for the first minute. | D40: Number only (no 'Same'). | E40: 110
A41: I | B41: Straddle | C41: Result of your straddle order. | D41: ▼ TP / SL / BE / N/A. | E41: TP
A42: J | B42: Scam Wick (15 sec before) | C42: Size of the fake move in the 15 seconds before the release (points). | D42: Number. | E42: 6
A43: K | B43: Notes | C43: Anything unusual: delayed release, FOMC week, other news at 8:30, crazy spread... | D43: Free text. | E43: EXAMPLE ONLY
A44: L | B44: CPI vs forecast | C44: Was CPI hotter or cooler than expected? Compare CPI m/m and Core CPI m/m, actual vs forecast (ForexFactory history). | D44: ▼ Hotter = both higher, or one higher + one equal · Cooler = both lower, or one lower + one equal · In line = both equal · Mixed = one higher, one lower. | E44: Cooler
A45: M | B45: Move vs data (auto) | C45: Did NQ move the 'logical' way? Hot CPI usually = NQ down, cool CPI = NQ up. | D45: Nothing - auto: With data / Against data / Neutral data (in line or mixed). | E45: With data
A46: N | B46: 1m candle close | C46: Where the 8:30 one-minute candle closed inside its own range (wicks included). | D46: ▼ Split the candle high-to-low into 3 equal parts: Top / Middle / Bottom third. | E46: Top
A47: O | B47: 5m candle close | C47: Where the 5-minute candle 8:30-8:34 closed inside its range. | D47: ▼ Top / Middle / Bottom third. | E47: Top
A48: P | B48: 15m candle close | C48: Where the 15-minute candle 8:30-8:44 closed inside its range. | D48: ▼ Top / Middle / Bottom third. | E48: Middle
A49: Q | B49: 1-min HIGH taken (BSL) – when? | C49: When price first traded above the HIGH of the 8:30 1-min candle (buy-side liquidity). | D49: ▼ Time window in NY time. 'Not by 16:00' if it never happened that day. | E49: 5-15 min
A50: R | B50: 1-min LOW taken (SSL) – when? | C50: When price first traded below the LOW of the 8:30 1-min candle (sell-side liquidity). | D50: ▼ Time window in NY time. 'Not by 16:00' if it never happened that day. | E50: Not by 16:00
A51: S | B51: Deepest pullback % | C51: How far price came back from the 1-min main-side extreme toward the 8:30 open, BEFORE it broke that extreme (stop checking at 8:45). 0 = no pullback · 50 = half-way · 62-79 = OTE · 100 = back at the 8:30 open · 120 = 20% past the open. | D51: Number only: 62, not 62%. Fib with 0 on the 1-min main-side extreme and 100 on the 8:30 open. | E51: 62
A52: T | B52: Back to 8:30 open – when? | C52: First time price traded back at the 8:30 open after the main move started. | D52: ▼ Time window in NY time. 'Not by 16:00' if it never came back. | E52: 15-60 min
A53: U | B53: At the open, price… | C53: What price did once it came back to the 8:30 open - does it just grab the liquidity there and keep going? | D53: ▼ Swept & resumed = turned and made a new high/low in the main direction before taking the 1-min wick side · Broke through = took the 1-min wick side first · Chopped around = neither by 16:00 · Never came back. | E53: Swept & resumed
A54: V | B54: Outcome 8:31–8:45 (auto) | C54: What the main move did after the first minute. | D54: Nothing - auto from Main Move, Deepest pullback % and the main-side 'taken – when': Back to open = pullback reached 100 · Continued = main side taken by 8:45 (1-5 or 5-15 min) · Partial retrace = not taken by 8:45, pullback 50-99 · Stalled / chop = not taken by 8:45, pullback under 50. | E54: Continued
A55: W | B55: First side taken (auto) | C55: Which end of the 1-min candle got taken first, and whether that was the main-move side or the wick side. | D55: Nothing - auto from the two 'taken – when' columns. | E55: High first (main side)
A56: X | B56: Daily bias (before 8:30) | C56: Your higher-timeframe bias for the day, decided BEFORE you replay the release. | D56: ▼ Bullish / Bearish / No bias. | E56: Bullish
A57: Y | B57: 8:30 open vs Midnight open | C57: Is the 8:30 open above the 00:00 New York opening price (premium) or below it (discount)? | D57: ▼ Above (premium) / Below (discount). | E57: Below (discount)
A58: Z | B58: Liquidity taken by wick | C58: Biggest liquidity level the first spike (wick) took. | D58: ▼ The biggest one taken: Prev week > Prev day > London > Asia > Pre-news > None. | E58: Pre-news high/low
A59: AA | B59: Liquidity taken by main move (by 8:45) | C59: Biggest liquidity level the main move took by 8:45. | D59: ▼ The biggest one taken: Prev week > Prev day > London > Asia > Pre-news > None. | E59: London high/low
A60: AB | B60: HTF PD array at extreme (optional) | C60: Did the main move's extreme (by 8:45) tap a 15m / 1H / 4H PD array? | D60: ▼ No / FVG / Order block / Breaker / Other. | E60: FVG
A61: AC | B61: 1m FVG from main move | C61: The first 1m fair value gap the main move left - what happened the first time price came back to it? | D61: ▼ No FVG · Never came back (by 16:00) · Came back & held (no 1m close beyond its far edge) · Came back & failed (IFVG = a 1m candle closed beyond its far edge). | E61: Came back & held
A62: AD | B62: SMT with ES (optional) | C62: At the main-move extreme, did NQ make a new high/low while ES didn't (or the other way round)? | D62: ▼ Yes / No / Not checked. | E62: Not checked
A63: AE | B63: Setup | C63: Which of your setups triggered, using fixed rules (see SETUPS TO TEST). | D63: ▼ None / A Continuation / B Reversal / C Open sweep / D 9:30-11:00 raid. | E63: A Continuation
A64: AF | B64: Result (R) | C64: Result of that setup in R (multiples of your risk). | D64: Number: 2 = +2R · -1 = full stop · 0 = breakeven. Leave empty if no setup. | E64: 2
A65: AG | B65: Chart link | C65: TradingView snapshot of the day, so you can see it again in one click. | D65: Camera icon → Copy link → paste here. | E65: tradingview.com/x/…
A67: SETUPS TO TEST
B68: A Continuation | C68: Main move leaves a 1m FVG → enter on the first pullback into it (Stats table 6 shows how deep pullbacks usually go) → stop beyond the pullback's swing → target the 1-min main side, then the next liquidity.
B69: B Reversal | C69: Main move takes a key level (London / prev day) or taps an HTF PD array, ideally with SMT → 1m MSS back through the last swing + IFVG → enter on the retrace → stop beyond the extreme → target the 8:30 open, then the 1-min wick side.
B70: C Open sweep | C70: Price comes back to the 8:30 open, sweeps it, then shifts back in the main direction (1m MSS) → enter → stop beyond the sweep → target the 1-min main side.
B71: D 9:30-11:00 raid | C71: After 9:30 price takes one side of the 1-min candle, then MSS + FVG → enter → target the other side.
B72: Rules first | C72: Write exact entry / stop / target rules for each setup BEFORE you backtest and never change them mid-test. Log every trigger, winners and losers. No valid trigger = Setup 'None'.
A74: REPLAY ROUTINE (ICT checklist) - the columns follow this order
B75: Step | C75: What to check | D75: Columns you fill
B76: 1 · 8:29 (pause) | C76: Mark Asia, London and pre-news (7:00-8:29) highs/lows, previous day/week high/low, the Midnight open and any 15m/1H/4H FVG or order block near price. | D76: Daily bias · 8:30 open vs Midnight open
B77: 2 · 8:30:00-8:30:59 | C77: 15s chart: first spike, main move, how far in 15s/30s/1m, straddle, scam wick. Which level did the wick take? Did the main move leave a 1m FVG? | D77: Your columns · Liquidity taken by wick
B78: 3 · 8:31-8:45 | C78: 1m chart: candle closes, deepest pullback with the Fib, which level the main move took, PD array at the extreme, SMT with ES. Look up the CPI actual vs forecast. | D78: CPI vs forecast · Candle closes · Deepest pullback % · Liquidity by main move · PD array · SMT
B79: 4 · until 16:00 | C79: When the 1-min HIGH and LOW got taken, when price came back to the 8:30 open and what it did there, and what happened when price came back to the 1m FVG. | D79: HIGH/LOW taken · Back to open · At the open · 1m FVG
B80: 5 · Review | C80: Did a setup trigger by your rules? Record it and the result in R, save the chart link, and check the grey auto columns make sense. | D80: Setup · Result (R) · Chart link
